{
    "ticker": "AFJKU",
    "queryCount": 96,
    "resultsCount": 96,
    "adjusted": true,
    "results": [
        {
            "v": 6856249.0,
            "vw": 10.1922,
            "o": 10.21,
            "c": 10.15,
            "h": 10.23,
            "l": 10.15,
            "t": 1701666000000,
            "n": 2924
        },
        {
            "v": 417448,
            "vw": 10.153,
            "o": 10.14,
            "c": 10.16,
            "h": 10.17,
            "l": 10.14,
            "t": 1701752400000,
            "n": 296
        },
        {
            "v": 70271,
            "vw": 10.1618,
            "o": 10.17,
            "c": 10.16,
            "h": 10.17,
            "l": 10.1598,
            "t": 1701838800000,
            "n": 158
        },
        {
            "v": 18014,
            "vw": 10.1696,
            "o": 10.17,
            "c": 10.16,
            "h": 10.17,
            "l": 10.16,
            "t": 1701925200000,
            "n": 46
        },
        {
            "v": 50881,
            "vw": 10.161,
            "o": 10.17,
            "c": 10.16,
            "h": 10.17,
            "l": 10.1501,
            "t": 1702011600000,
            "n": 100
        },
        {
            "v": 32797,
            "vw": 10.1595,
            "o": 10.16,
            "c": 10.15,
            "h": 10.16,
            "l": 10.15,
            "t": 1702270800000,
            "n": 61
        },
        {
            "v": 31643,
            "vw": 10.1603,
            "o": 10.16,
            "c": 10.16,
            "h": 10.17,
            "l": 10.16,
            "t": 1702357200000,
            "n": 28
        },
        {
            "v": 520,
            "vw": 10.1583,
            "o": 10.16,
            "c": 10.1558,
            "h": 10.16,
            "l": 10.1558,
            "t": 1702443600000,
            "n": 11
        },
        {
            "v": 209461,
            "vw": 10.1604,
            "o": 10.15,
            "c": 10.17,
            "h": 10.17,
            "l": 10.15,
            "t": 1702530000000,
            "n": 129
        },
        {
            "v": 158539,
            "vw": 10.1601,
            "o": 10.17,
            "c": 10.16,
            "h": 10.17,
            "l": 10.16,
            "t": 1702616400000,
            "n": 176
        },
        {
            "v": 306494,
            "vw": 10.1707,
            "o": 10.17,
            "c": 10.17,
            "h": 10.19,
            "l": 10.1699,
            "t": 1702875600000,
            "n": 74
        },
        {
            "v": 164969,
            "vw": 10.17,
            "o": 10.17,
            "c": 10.17,
            "h": 10.17,
            "l": 10.17,
            "t": 1702962000000,
            "n": 153
        },
        {
            "v": 211752,
            "vw": 10.17,
            "o": 10.17,
            "c": 10.17,
            "h": 10.17,
            "l": 10.17,
            "t": 1703048400000,
            "n": 85
        },
        {
            "v": 105146,
            "vw": 10.1762,
            "o": 10.17,
            "c": 10.19,
            "h": 10.19,
            "l": 10.17,
            "t": 1703134800000,
            "n": 14
        },
        {
            "v": 4972,
            "vw": 10.1922,
            "o": 10.18,
            "c": 10.19,
            "h": 10.2,
            "l": 10.18,
            "t": 1703221200000,
            "n": 18
        },
        {
            "v": 2838,
            "vw": 10.1902,
            "o": 10.1901,
            "c": 10.19,
            "h": 10.1901,
            "l": 10.19,
            "t": 1703653200000,
            "n": 10
        },
        {
            "v": 3014,
            "vw": 10.2,
            "o": 10.2,
            "c": 10.2,
            "h": 10.2,
            "l": 10.2,
            "t": 1703826000000,
            "n": 4
        },
        {
            "v": 3100,
            "vw": 10.2125,
            "o": 10.2,
            "c": 10.22,
            "h": 10.22,
            "l": 10.2,
            "t": 1704171600000,
            "n": 11
        },
        {
            "v": 8303,
            "vw": 10.2453,
            "o": 10.24,
            "c": 10.24,
            "h": 10.25,
            "l": 10.225,
            "t": 1704258000000,
            "n": 20
        },
        {
            "v": 59941,
            "vw": 10.2441,
            "o": 10.23,
            "c": 10.24,
            "h": 10.25,
            "l": 10.23,
            "t": 1704344400000,
            "n": 91
        },
        {
            "v": 13639,
            "vw": 10.2509,
            "o": 10.2613,
            "c": 10.25,
            "h": 10.2613,
            "l": 10.25,
            "t": 1704430800000,
            "n": 28
        },
        {
            "v": 834,
            "vw": 10.2554,
            "o": 10.26,
            "c": 10.26,
            "h": 10.26,
            "l": 10.26,
            "t": 1704690000000,
            "n": 20
        },
        {
            "v": 71849,
            "vw": 10.2501,
            "o": 10.25,
            "c": 10.26,
            "h": 10.26,
            "l": 10.25,
            "t": 1704776400000,
            "n": 11
        },
        {
            "v": 27724,
            "vw": 10.27,
            "o": 10.27,
            "c": 10.27,
            "h": 10.27,
            "l": 10.27,
            "t": 1704862800000,
            "n": 43
        },
        {
            "v": 903,
            "vw": 10.28,
            "o": 10.28,
            "c": 10.28,
            "h": 10.28,
            "l": 10.28,
            "t": 1705381200000,
            "n": 12
        },
        {
            "v": 32722,
            "vw": 10.297,
            "o": 10.28,
            "c": 10.3,
            "h": 10.3,
            "l": 10.28,
            "t": 1705467600000,
            "n": 21
        },
        {
            "v": 637,
            "vw": 10.2963,
            "o": 10.28,
            "c": 10.3,
            "h": 10.3,
            "l": 10.28,
            "t": 1705554000000,
            "n": 7
        },
        {
            "v": 515,
            "vw": 10.32,
            "o": 10.32,
            "c": 10.32,
            "h": 10.32,
            "l": 10.32,
            "t": 1705640400000,
            "n": 6
        },
        {
            "v": 250099,
            "vw": 10.3445,
            "o": 10.34,
            "c": 10.34,
            "h": 10.35,
            "l": 10.31,
            "t": 1705899600000,
            "n": 208
        },
        {
            "v": 38290,
            "vw": 10.3399,
            "o": 10.34,
            "c": 10.34,
            "h": 10.34,
            "l": 10.34,
            "t": 1705986000000,
            "n": 20
        },
        {
            "v": 5380,
            "vw": 10.4,
            "o": 10.4,
            "c": 10.4,
            "h": 10.4,
            "l": 10.4,
            "t": 1706504400000,
            "n": 18
        },
        {
            "v": 1962,
            "vw": 10.6488,
            "o": 10.6629,
            "c": 10.4602,
            "h": 11.314,
            "l": 10.34,
            "t": 1706677200000,
            "n": 22
        },
        {
            "v": 6060,
            "vw": 10.542,
            "o": 11.0951,
            "c": 10.37,
            "h": 11.0951,
            "l": 10.34,
            "t": 1706763600000,
            "n": 33
        },
        {
            "v": 124,
            "vw": 10.3597,
            "o": 10.35,
            "c": 10.35,
            "h": 10.35,
            "l": 10.35,
            "t": 1706850000000,
            "n": 2
        },
        {
            "v": 2001,
            "vw": 10.4239,
            "o": 10.36,
            "c": 10.5259,
            "h": 10.5259,
            "l": 10.35,
            "t": 1707282000000,
            "n": 10
        },
        {
            "v": 1189,
            "vw": 10.3858,
            "o": 10.469,
            "c": 10.3401,
            "h": 10.52,
            "l": 10.34,
            "t": 1707368400000,
            "n": 9
        },
        {
            "v": 130,
            "vw": 10.3793,
            "o": 10.35,
            "c": 10.35,
            "h": 10.35,
            "l": 10.35,
            "t": 1708405200000,
            "n": 4
        },
        {
            "v": 501,
            "vw": 10.3719,
            "o": 10.37,
            "c": 10.37,
            "h": 10.37,
            "l": 10.37,
            "t": 1708923600000,
            "n": 5
        },
        {
            "v": 540,
            "vw": 10.4736,
            "o": 10.5,
            "c": 10.5,
            "h": 10.5,
            "l": 10.5,
            "t": 1709269200000,
            "n": 11
        },
        {
            "v": 10829,
            "vw": 10.3701,
            "o": 10.37,
            "c": 10.37,
            "h": 10.37,
            "l": 10.37,
            "t": 1709787600000,
            "n": 31
        },
        {
            "v": 39983,
            "vw": 10.37,
            "o": 10.37,
            "c": 10.37,
            "h": 10.37,
            "l": 10.37,
            "t": 1710129600000,
            "n": 2
        },
        {
            "v": 100,
            "vw": 10.36,
            "o": 10.36,
            "c": 10.36,
            "h": 10.36,
            "l": 10.36,
            "t": 1710820800000,
            "n": 1
        },
        {
            "v": 112,
            "vw": 10.3511,
            "o": 10.35,
            "c": 10.35,
            "h": 10.35,
            "l": 10.35,
            "t": 1710993600000,
            "n": 2
        },
        {
            "v": 159,
            "vw": 10.3637,
            "o": 10.36,
            "c": 10.36,
            "h": 10.36,
            "l": 10.36,
            "t": 1711080000000,
            "n": 2
        },
        {
            "v": 2560,
            "vw": 10.7391,
            "o": 10.55,
            "c": 10.4,
            "h": 11.41,
            "l": 10.4,
            "t": 1711425600000,
            "n": 54
        },
        {
            "v": 3870,
            "vw": 10.8765,
            "o": 10.89,
            "c": 10.66,
            "h": 11.63,
            "l": 10.5,
            "t": 1711512000000,
            "n": 51
        },
        {
            "v": 1999,
            "vw": 11.034,
            "o": 10.93,
            "c": 10.87,
            "h": 11.39,
            "l": 10.84,
            "t": 1711598400000,
            "n": 54
        },
        {
            "v": 324,
            "vw": 11.0693,
            "o": 11.25,
            "c": 11.02,
            "h": 11.25,
            "l": 11.02,
            "t": 1711944000000,
            "n": 6
        },
        {
            "v": 502,
            "vw": 10.7513,
            "o": 10.75,
            "c": 10.75,
            "h": 10.75,
            "l": 10.75,
            "t": 1712030400000,
            "n": 3
        },
        {
            "v": 354,
            "vw": 10.5636,
            "o": 10.56,
            "c": 10.56,
            "h": 10.56,
            "l": 10.56,
            "t": 1712289600000,
            "n": 6
        },
        {
            "v": 703,
            "vw": 10.5514,
            "o": 10.56,
            "c": 10.55,
            "h": 10.56,
            "l": 10.55,
            "t": 1712548800000,
            "n": 5
        },
        {
            "v": 131,
            "vw": 10.4171,
            "o": 10.41,
            "c": 10.41,
            "h": 10.41,
            "l": 10.41,
            "t": 1712808000000,
            "n": 3
        },
        {
            "v": 102,
            "vw": 10.45,
            "o": 10.45,
            "c": 10.45,
            "h": 10.45,
            "l": 10.45,
            "t": 1713499200000,
            "n": 2
        },
        {
            "v": 103,
            "vw": 10.4504,
            "o": 10.45,
            "c": 10.45,
            "h": 10.45,
            "l": 10.45,
            "t": 1713758400000,
            "n": 4
        },
        {
            "v": 500,
            "vw": 10.494,
            "o": 10.5,
            "c": 10.47,
            "h": 10.5,
            "l": 10.47,
            "t": 1713844800000,
            "n": 5
        },
        {
            "v": 201,
            "vw": 10.4002,
            "o": 10.4,
            "c": 10.4,
            "h": 10.4,
            "l": 10.4,
            "t": 1714449600000,
            "n": 2
        },
        {
            "v": 900,
            "vw": 10.38,
            "o": 10.31,
            "c": 10.4,
            "h": 10.4,
            "l": 10.31,
            "t": 1714622400000,
            "n": 8
        },
        {
            "v": 800,
            "vw": 10.4088,
            "o": 10.4,
            "c": 10.41,
            "h": 10.41,
            "l": 10.4,
            "t": 1715140800000,
            "n": 4
        },
        {
            "v": 100,
            "vw": 10.43,
            "o": 10.43,
            "c": 10.43,
            "h": 10.43,
            "l": 10.43,
            "t": 1715832000000,
            "n": 1
        },
        {
            "v": 100,
            "vw": 10.43,
            "o": 10.43,
            "c": 10.43,
            "h": 10.43,
            "l": 10.43,
            "t": 1715918400000,
            "n": 1
        },
        {
            "v": 101,
            "vw": 10.4508,
            "o": 10.45,
            "c": 10.45,
            "h": 10.45,
            "l": 10.45,
            "t": 1716177600000,
            "n": 2
        },
        {
            "v": 100,
            "vw": 10.43,
            "o": 10.43,
            "c": 10.43,
            "h": 10.43,
            "l": 10.43,
            "t": 1716264000000,
            "n": 1
        },
        {
            "v": 100,
            "vw": 10.39,
            "o": 10.39,
            "c": 10.39,
            "h": 10.39,
            "l": 10.39,
            "t": 1716350400000,
            "n": 1
        },
        {
            "v": 100,
            "vw": 10.52,
            "o": 10.52,
            "c": 10.52,
            "h": 10.52,
            "l": 10.52,
            "t": 1717473600000,
            "n": 1
        },
        {
            "v": 100,
            "vw": 10.51,
            "o": 10.51,
            "c": 10.51,
            "h": 10.51,
            "l": 10.51,
            "t": 1717560000000,
            "n": 1
        },
        {
            "v": 100,
            "vw": 10.48,
            "o": 10.48,
            "c": 10.48,
            "h": 10.48,
            "l": 10.48,
            "t": 1717732800000,
            "n": 1
        },
        {
            "v": 111,
            "vw": 10.48,
            "o": 10.48,
            "c": 10.48,
            "h": 10.48,
            "l": 10.48,
            "t": 1717992000000,
            "n": 3
        },
        {
            "v": 125,
            "vw": 10.4814,
            "o": 10.48,
            "c": 10.48,
            "h": 10.48,
            "l": 10.48,
            "t": 1718078400000,
            "n": 2
        },
        {
            "v": 100,
            "vw": 10.48,
            "o": 10.48,
            "c": 10.48,
            "h": 10.48,
            "l": 10.48,
            "t": 1718856000000,
            "n": 1
        },
        {
            "v": 100,
            "vw": 10.55,
            "o": 10.55,
            "c": 10.55,
            "h": 10.55,
            "l": 10.55,
            "t": 1718942400000,
            "n": 1
        },
        {
            "v": 205509,
            "vw": 10.55,
            "o": 10.55,
            "c": 10.54,
            "h": 10.55,
            "l": 10.54,
            "t": 1719201600000,
            "n": 12
        },
        {
            "v": 79696,
            "vw": 10.5532,
            "o": 10.55,
            "c": 10.56,
            "h": 10.56,
            "l": 10.55,
            "t": 1719288000000,
            "n": 27
        },
        {
            "v": 100,
            "vw": 10.56,
            "o": 10.56,
            "c": 10.56,
            "h": 10.56,
            "l": 10.56,
            "t": 1720152000000,
            "n": 1
        },
        {
            "v": 200,
            "vw": 10.555,
            "o": 10.56,
            "c": 10.55,
            "h": 10.56,
            "l": 10.55,
            "t": 1720411200000,
            "n": 2
        },
        {
            "v": 179,
            "vw": 10.55,
            "o": 10.55,
            "c": 10.55,
            "h": 10.55,
            "l": 10.55,
            "t": 1721016000000,
            "n": 1
        },
        {
            "v": 100,
            "vw": 10.56,
            "o": 10.56,
            "c": 10.56,
            "h": 10.56,
            "l": 10.56,
            "t": 1721707200000,
            "n": 1
        },
        {
            "v": 109,
            "vw": 10.6361,
            "o": 10.58,
            "c": 10.58,
            "h": 10.58,
            "l": 10.58,
            "t": 1721880000000,
            "n": 2
        },
        {
            "v": 209500,
            "vw": 10.65,
            "o": 10.65,
            "c": 10.65,
            "h": 10.65,
            "l": 10.65,
            "t": 1724299200000,
            "n": 5
        },
        {
            "v": 1600,
            "vw": 10.95,
            "o": 10.95,
            "c": 10.95,
            "h": 10.95,
            "l": 10.95,
            "t": 1727236800000,
            "n": 2
        },
        {
            "v": 3403,
            "vw": 10.5362,
            "o": 10.55,
            "c": 10.53,
            "h": 10.55,
            "l": 10.51,
            "t": 1729051200000,
            "n": 19
        },
        {
            "v": 29864,
            "vw": 10.7332,
            "o": 10.51,
            "c": 11.12,
            "h": 12.06,
            "l": 10.51,
            "t": 1729137600000,
            "n": 28
        },
        {
            "v": 1401,
            "vw": 11.512,
            "o": 11.68,
            "c": 11.33,
            "h": 12.69,
            "l": 10.99,
            "t": 1729569600000,
            "n": 15
        },
        {
            "v": 1117,
            "vw": 11.0296,
            "o": 10.9801,
            "c": 11.1,
            "h": 11.1,
            "l": 10.98,
            "t": 1729656000000,
            "n": 26
        },
        {
            "v": 15366,
            "vw": 11.1908,
            "o": 11.14,
            "c": 10.91,
            "h": 11.94,
            "l": 10.8,
            "t": 1730088000000,
            "n": 107
        },
        {
            "v": 7712,
            "vw": 10.6869,
            "o": 10.8,
            "c": 11,
            "h": 11,
            "l": 10.66,
            "t": 1730174400000,
            "n": 37
        },
        {
            "v": 404,
            "vw": 10.7835,
            "o": 10.79,
            "c": 10.75,
            "h": 10.79,
            "l": 10.7,
            "t": 1730260800000,
            "n": 8
        },
        {
            "v": 110,
            "vw": 10.7941,
            "o": 10.74,
            "c": 10.74,
            "h": 10.74,
            "l": 10.74,
            "t": 1733115600000,
            "n": 3
        },
        {
            "v": 612,
            "vw": 10.9294,
            "o": 10.79,
            "c": 11.035,
            "h": 11.035,
            "l": 10.79,
            "t": 1733806800000,
            "n": 10
        },
        {
            "v": 306,
            "vw": 10.95,
            "o": 10.95,
            "c": 10.95,
            "h": 10.95,
            "l": 10.95,
            "t": 1733893200000,
            "n": 3
        },
        {
            "v": 322,
            "vw": 10.9429,
            "o": 11.2,
            "c": 10.75,
            "h": 11.2,
            "l": 10.75,
            "t": 1737954000000,
            "n": 6
        },
        {
            "v": 454,
            "vw": 11.2194,
            "o": 11.3,
            "c": 11.2,
            "h": 11.3,
            "l": 11.2,
            "t": 1738731600000,
            "n": 10
        },
        {
            "v": 200,
            "vw": 11.105,
            "o": 11.2,
            "c": 11.01,
            "h": 11.2,
            "l": 11.01,
            "t": 1739163600000,
            "n": 2
        },
        {
            "v": 100,
            "vw": 11.3,
            "o": 11.3,
            "c": 11.3,
            "h": 11.3,
            "l": 11.3,
            "t": 1739250000000,
            "n": 1
        },
        {
            "v": 6672,
            "vw": 11.6277,
            "o": 11.5,
            "c": 11.49,
            "h": 12.35,
            "l": 11.24,
            "t": 1742356800000,
            "n": 59
        },
        {
            "v": 11220,
            "vw": 11.864,
            "o": 12,
            "c": 11.21,
            "h": 12.9,
            "l": 11.15,
            "t": 1742529600000,
            "n": 103
        },
        {
            "v": 1726,
            "vw": 11.2595,
            "o": 11.39,
            "c": 11.25,
            "h": 11.39,
            "l": 11.21,
            "t": 1742788800000,
            "n": 21
        }
    ],
    "status": "DELAYED",
    "request_id": "31bb2595548b4063144030721e19a931",
    "count": 96
}