{
    "ticker": "ATMC",
    "queryCount": 206,
    "resultsCount": 206,
    "adjusted": true,
    "results": [
        {
            "v": 732,
            "vw": 10.3993,
            "o": 10.392,
            "c": 10.4,
            "h": 10.4,
            "l": 10.392,
            "t": 1688529600000,
            "n": 9
        },
        {
            "v": 677,
            "vw": 10.3914,
            "o": 10.39,
            "c": 10.39,
            "h": 10.39,
            "l": 10.39,
            "t": 1688616000000,
            "n": 4
        },
        {
            "v": 2400,
            "vw": 10.3803,
            "o": 10.3803,
            "c": 10.3803,
            "h": 10.3803,
            "l": 10.3803,
            "t": 1688702400000,
            "n": 2
        },
        {
            "v": 101,
            "vw": 10.4642,
            "o": 10.465,
            "c": 10.465,
            "h": 10.465,
            "l": 10.465,
            "t": 1689048000000,
            "n": 2
        },
        {
            "v": 440898,
            "vw": 10.4077,
            "o": 10.41,
            "c": 10.4,
            "h": 10.42,
            "l": 10.4,
            "t": 1689134400000,
            "n": 43
        },
        {
            "v": 5000,
            "vw": 10.4,
            "o": 10.4,
            "c": 10.4,
            "h": 10.4,
            "l": 10.4,
            "t": 1689220800000,
            "n": 1
        },
        {
            "v": 2000,
            "vw": 10.4,
            "o": 10.4,
            "c": 10.4,
            "h": 10.4,
            "l": 10.4,
            "t": 1689307200000,
            "n": 1
        },
        {
            "v": 13076,
            "vw": 10.41,
            "o": 10.41,
            "c": 10.41,
            "h": 10.41,
            "l": 10.41,
            "t": 1689566400000,
            "n": 62
        },
        {
            "v": 4020,
            "vw": 10.41,
            "o": 10.41,
            "c": 10.41,
            "h": 10.41,
            "l": 10.41,
            "t": 1689652800000,
            "n": 9
        },
        {
            "v": 34737,
            "vw": 10.4306,
            "o": 10.42,
            "c": 10.42,
            "h": 10.55,
            "l": 10.42,
            "t": 1689739200000,
            "n": 26
        },
        {
            "v": 155584,
            "vw": 10.4107,
            "o": 10.41,
            "c": 10.43,
            "h": 10.43,
            "l": 10.41,
            "t": 1689825600000,
            "n": 10
        },
        {
            "v": 101,
            "vw": 10.4202,
            "o": 10.42,
            "c": 10.42,
            "h": 10.42,
            "l": 10.42,
            "t": 1690516800000,
            "n": 2
        },
        {
            "v": 57502,
            "vw": 10.4402,
            "o": 10.44,
            "c": 10.45,
            "h": 10.45,
            "l": 10.44,
            "t": 1690862400000,
            "n": 23
        },
        {
            "v": 307,
            "vw": 10.6518,
            "o": 10.5,
            "c": 10.495,
            "h": 10.5,
            "l": 10.495,
            "t": 1691035200000,
            "n": 8
        },
        {
            "v": 1166,
            "vw": 10.5043,
            "o": 10.55,
            "c": 10.44,
            "h": 10.55,
            "l": 10.44,
            "t": 1691121600000,
            "n": 15
        },
        {
            "v": 419,
            "vw": 10.44,
            "o": 10.44,
            "c": 10.44,
            "h": 10.44,
            "l": 10.44,
            "t": 1691467200000,
            "n": 1
        },
        {
            "v": 150,
            "vw": 10.4467,
            "o": 10.45,
            "c": 10.45,
            "h": 10.45,
            "l": 10.45,
            "t": 1691985600000,
            "n": 2
        },
        {
            "v": 100,
            "vw": 10.45,
            "o": 10.45,
            "c": 10.45,
            "h": 10.45,
            "l": 10.45,
            "t": 1692072000000,
            "n": 1
        },
        {
            "v": 400,
            "vw": 10.4476,
            "o": 10.4603,
            "c": 10.45,
            "h": 10.4603,
            "l": 10.44,
            "t": 1692158400000,
            "n": 4
        },
        {
            "v": 572,
            "vw": 10.45,
            "o": 10.45,
            "c": 10.45,
            "h": 10.45,
            "l": 10.45,
            "t": 1692590400000,
            "n": 1
        },
        {
            "v": 9269,
            "vw": 10.5403,
            "o": 10.545,
            "c": 10.54,
            "h": 10.545,
            "l": 10.54,
            "t": 1692676800000,
            "n": 30
        },
        {
            "v": 5738,
            "vw": 10.5401,
            "o": 10.54,
            "c": 10.54,
            "h": 10.54,
            "l": 10.54,
            "t": 1692763200000,
            "n": 19
        },
        {
            "v": 5771,
            "vw": 10.5401,
            "o": 10.54,
            "c": 10.5401,
            "h": 10.5401,
            "l": 10.54,
            "t": 1692849600000,
            "n": 8
        },
        {
            "v": 6604,
            "vw": 10.55,
            "o": 10.55,
            "c": 10.55,
            "h": 10.55,
            "l": 10.55,
            "t": 1693368000000,
            "n": 25
        },
        {
            "v": 16793,
            "vw": 10.5514,
            "o": 10.55,
            "c": 10.55,
            "h": 10.565,
            "l": 10.55,
            "t": 1693886400000,
            "n": 24
        },
        {
            "v": 600,
            "vw": 10.55,
            "o": 10.55,
            "c": 10.55,
            "h": 10.55,
            "l": 10.55,
            "t": 1693972800000,
            "n": 1
        },
        {
            "v": 7856,
            "vw": 10.4849,
            "o": 10.52,
            "c": 10.46,
            "h": 10.52,
            "l": 10.46,
            "t": 1694059200000,
            "n": 37
        },
        {
            "v": 26818,
            "vw": 10.5,
            "o": 10.5,
            "c": 10.5,
            "h": 10.5,
            "l": 10.5,
            "t": 1694491200000,
            "n": 80
        },
        {
            "v": 38543,
            "vw": 10.5203,
            "o": 10.52,
            "c": 10.5001,
            "h": 10.55,
            "l": 10.5001,
            "t": 1694750400000,
            "n": 5
        },
        {
            "v": 7506,
            "vw": 10.555,
            "o": 10.56,
            "c": 10.55,
            "h": 10.56,
            "l": 10.55,
            "t": 1695009600000,
            "n": 17
        },
        {
            "v": 502,
            "vw": 10.5,
            "o": 10.5,
            "c": 10.5,
            "h": 10.5,
            "l": 10.5,
            "t": 1695096000000,
            "n": 2
        },
        {
            "v": 3446,
            "vw": 10.5468,
            "o": 10.55,
            "c": 10.5534,
            "h": 10.5534,
            "l": 10.53,
            "t": 1695700800000,
            "n": 9
        },
        {
            "v": 2600,
            "vw": 10.5544,
            "o": 10.565,
            "c": 10.56,
            "h": 10.565,
            "l": 10.53,
            "t": 1696305600000,
            "n": 16
        },
        {
            "v": 5101,
            "vw": 10.61,
            "o": 10.61,
            "c": 10.61,
            "h": 10.61,
            "l": 10.61,
            "t": 1696392000000,
            "n": 1
        },
        {
            "v": 119990,
            "vw": 10.64,
            "o": 10.64,
            "c": 10.64,
            "h": 10.64,
            "l": 10.63,
            "t": 1696910400000,
            "n": 12
        },
        {
            "v": 507,
            "vw": 10.6852,
            "o": 10.685,
            "c": 10.685,
            "h": 10.685,
            "l": 10.685,
            "t": 1697169600000,
            "n": 4
        },
        {
            "v": 106,
            "vw": 10.6513,
            "o": 10.65,
            "c": 10.65,
            "h": 10.65,
            "l": 10.65,
            "t": 1697601600000,
            "n": 4
        },
        {
            "v": 353724,
            "vw": 10.6799,
            "o": 10.68,
            "c": 10.67,
            "h": 10.68,
            "l": 10.67,
            "t": 1697774400000,
            "n": 33
        },
        {
            "v": 443806,
            "vw": 10.6862,
            "o": 10.65,
            "c": 10.69,
            "h": 10.69,
            "l": 10.65,
            "t": 1698033600000,
            "n": 17
        },
        {
            "v": 1200,
            "vw": 10.6814,
            "o": 10.68,
            "c": 10.6833,
            "h": 10.6833,
            "l": 10.68,
            "t": 1698206400000,
            "n": 3
        },
        {
            "v": 57398,
            "vw": 10.69,
            "o": 10.69,
            "c": 10.69,
            "h": 10.69,
            "l": 10.69,
            "t": 1698292800000,
            "n": 26
        },
        {
            "v": 557,
            "vw": 10.6911,
            "o": 10.6901,
            "c": 10.69,
            "h": 10.6901,
            "l": 10.69,
            "t": 1698638400000,
            "n": 24
        },
        {
            "v": 1001,
            "vw": 10.69,
            "o": 10.69,
            "c": 10.69,
            "h": 10.69,
            "l": 10.69,
            "t": 1698811200000,
            "n": 2
        },
        {
            "v": 516,
            "vw": 10.69,
            "o": 10.69,
            "c": 10.69,
            "h": 10.69,
            "l": 10.69,
            "t": 1698897600000,
            "n": 4
        },
        {
            "v": 27550,
            "vw": 10.7,
            "o": 10.7,
            "c": 10.7,
            "h": 10.7,
            "l": 10.7,
            "t": 1699246800000,
            "n": 17
        },
        {
            "v": 78501,
            "vw": 10.6996,
            "o": 10.7,
            "c": 10.7,
            "h": 10.7,
            "l": 10.69,
            "t": 1699333200000,
            "n": 14
        },
        {
            "v": 400,
            "vw": 10.71,
            "o": 10.71,
            "c": 10.71,
            "h": 10.71,
            "l": 10.71,
            "t": 1699851600000,
            "n": 4
        },
        {
            "v": 1027,
            "vw": 10.71,
            "o": 10.71,
            "c": 10.71,
            "h": 10.71,
            "l": 10.71,
            "t": 1700024400000,
            "n": 1
        },
        {
            "v": 100000,
            "vw": 10.71,
            "o": 10.71,
            "c": 10.71,
            "h": 10.71,
            "l": 10.71,
            "t": 1700542800000,
            "n": 1
        },
        {
            "v": 256917,
            "vw": 10.7275,
            "o": 10.72,
            "c": 10.74,
            "h": 10.74,
            "l": 10.71,
            "t": 1701147600000,
            "n": 228
        },
        {
            "v": 150386,
            "vw": 10.7298,
            "o": 10.73,
            "c": 10.72,
            "h": 10.73,
            "l": 10.72,
            "t": 1701234000000,
            "n": 21
        },
        {
            "v": 831,
            "vw": 10.7242,
            "o": 10.72,
            "c": 10.73,
            "h": 10.73,
            "l": 10.72,
            "t": 1701406800000,
            "n": 9
        },
        {
            "v": 2200,
            "vw": 10.74,
            "o": 10.74,
            "c": 10.74,
            "h": 10.74,
            "l": 10.74,
            "t": 1701666000000,
            "n": 1
        },
        {
            "v": 908,
            "vw": 10.7412,
            "o": 10.743,
            "c": 10.743,
            "h": 10.743,
            "l": 10.743,
            "t": 1701752400000,
            "n": 2
        },
        {
            "v": 615,
            "vw": 10.6929,
            "o": 10.7,
            "c": 10.7,
            "h": 10.7,
            "l": 10.7,
            "t": 1701838800000,
            "n": 2
        },
        {
            "v": 7870,
            "vw": 10.7063,
            "o": 10.7063,
            "c": 10.7063,
            "h": 10.7063,
            "l": 10.7063,
            "t": 1701925200000,
            "n": 2
        },
        {
            "v": 7810,
            "vw": 10.75,
            "o": 10.75,
            "c": 10.75,
            "h": 10.75,
            "l": 10.75,
            "t": 1702011600000,
            "n": 3
        },
        {
            "v": 14625,
            "vw": 10.73,
            "o": 10.73,
            "c": 10.73,
            "h": 10.73,
            "l": 10.73,
            "t": 1702530000000,
            "n": 7
        },
        {
            "v": 708,
            "vw": 10.73,
            "o": 10.73,
            "c": 10.73,
            "h": 10.73,
            "l": 10.73,
            "t": 1702616400000,
            "n": 4
        },
        {
            "v": 2231,
            "vw": 10.9324,
            "o": 10.99,
            "c": 10.938,
            "h": 10.99,
            "l": 10.73,
            "t": 1702875600000,
            "n": 11
        },
        {
            "v": 102,
            "vw": 10.7208,
            "o": 10.72,
            "c": 10.72,
            "h": 10.72,
            "l": 10.72,
            "t": 1703653200000,
            "n": 3
        },
        {
            "v": 102,
            "vw": 10.73,
            "o": 10.73,
            "c": 10.73,
            "h": 10.73,
            "l": 10.73,
            "t": 1703739600000,
            "n": 2
        },
        {
            "v": 800,
            "vw": 10.8325,
            "o": 10.84,
            "c": 10.73,
            "h": 10.85,
            "l": 10.73,
            "t": 1703826000000,
            "n": 3
        },
        {
            "v": 132,
            "vw": 10.7859,
            "o": 10.75,
            "c": 10.75,
            "h": 10.75,
            "l": 10.75,
            "t": 1704171600000,
            "n": 7
        },
        {
            "v": 1100,
            "vw": 10.8,
            "o": 10.8,
            "c": 10.8,
            "h": 10.8,
            "l": 10.8,
            "t": 1704430800000,
            "n": 5
        },
        {
            "v": 1178,
            "vw": 10.7781,
            "o": 10.77,
            "c": 10.77,
            "h": 10.77,
            "l": 10.77,
            "t": 1704690000000,
            "n": 9
        },
        {
            "v": 1093,
            "vw": 10.7947,
            "o": 10.798,
            "c": 10.79,
            "h": 10.798,
            "l": 10.79,
            "t": 1704776400000,
            "n": 9
        },
        {
            "v": 179,
            "vw": 10.79,
            "o": 10.79,
            "c": 10.79,
            "h": 10.79,
            "l": 10.79,
            "t": 1705381200000,
            "n": 2
        },
        {
            "v": 3551,
            "vw": 10.7898,
            "o": 10.79,
            "c": 10.79,
            "h": 10.79,
            "l": 10.79,
            "t": 1705640400000,
            "n": 12
        },
        {
            "v": 31975,
            "vw": 10.8,
            "o": 10.8,
            "c": 10.8,
            "h": 10.8,
            "l": 10.8,
            "t": 1706504400000,
            "n": 9
        },
        {
            "v": 2900,
            "vw": 10.809,
            "o": 10.809,
            "c": 10.809,
            "h": 10.809,
            "l": 10.809,
            "t": 1706590800000,
            "n": 2
        },
        {
            "v": 191,
            "vw": 10.8048,
            "o": 10.8,
            "c": 10.8,
            "h": 10.8,
            "l": 10.8,
            "t": 1706677200000,
            "n": 5
        },
        {
            "v": 210,
            "vw": 10.8,
            "o": 10.8,
            "c": 10.8,
            "h": 10.8,
            "l": 10.8,
            "t": 1706850000000,
            "n": 2
        },
        {
            "v": 235,
            "vw": 10.8102,
            "o": 10.84,
            "c": 10.77,
            "h": 10.84,
            "l": 10.77,
            "t": 1707109200000,
            "n": 3
        },
        {
            "v": 1100,
            "vw": 10.8055,
            "o": 10.805,
            "c": 10.81,
            "h": 10.81,
            "l": 10.805,
            "t": 1707282000000,
            "n": 2
        },
        {
            "v": 6675,
            "vw": 10.81,
            "o": 10.81,
            "c": 10.81,
            "h": 10.81,
            "l": 10.81,
            "t": 1707714000000,
            "n": 5
        },
        {
            "v": 309,
            "vw": 10.8103,
            "o": 10.81,
            "c": 10.81,
            "h": 10.81,
            "l": 10.81,
            "t": 1707800400000,
            "n": 6
        },
        {
            "v": 7001,
            "vw": 10.83,
            "o": 10.83,
            "c": 10.83,
            "h": 10.83,
            "l": 10.83,
            "t": 1708059600000,
            "n": 27
        },
        {
            "v": 238,
            "vw": 10.84,
            "o": 10.84,
            "c": 10.84,
            "h": 10.84,
            "l": 10.84,
            "t": 1708405200000,
            "n": 4
        },
        {
            "v": 4185,
            "vw": 10.8629,
            "o": 10.85,
            "c": 10.89,
            "h": 10.89,
            "l": 10.85,
            "t": 1708491600000,
            "n": 8
        },
        {
            "v": 1159,
            "vw": 10.8471,
            "o": 10.8466,
            "c": 10.8466,
            "h": 10.8466,
            "l": 10.8466,
            "t": 1708923600000,
            "n": 4
        },
        {
            "v": 1612,
            "vw": 10.864,
            "o": 10.865,
            "c": 10.865,
            "h": 10.865,
            "l": 10.865,
            "t": 1709010000000,
            "n": 4
        },
        {
            "v": 1100,
            "vw": 10.86,
            "o": 10.86,
            "c": 10.86,
            "h": 10.86,
            "l": 10.86,
            "t": 1709096400000,
            "n": 1
        },
        {
            "v": 224,
            "vw": 10.8606,
            "o": 10.86,
            "c": 10.86,
            "h": 10.86,
            "l": 10.86,
            "t": 1709269200000,
            "n": 8
        },
        {
            "v": 50121,
            "vw": 10.848,
            "o": 10.86,
            "c": 10.86,
            "h": 10.86,
            "l": 10.86,
            "t": 1709528400000,
            "n": 292
        },
        {
            "v": 37557,
            "vw": 10.8921,
            "o": 10.89,
            "c": 10.9,
            "h": 10.9,
            "l": 10.89,
            "t": 1709701200000,
            "n": 23
        },
        {
            "v": 278,
            "vw": 10.9204,
            "o": 10.92,
            "c": 10.92,
            "h": 10.92,
            "l": 10.92,
            "t": 1710129600000,
            "n": 5
        },
        {
            "v": 78482,
            "vw": 10.9307,
            "o": 10.935,
            "c": 10.93,
            "h": 10.935,
            "l": 10.92,
            "t": 1710388800000,
            "n": 108
        },
        {
            "v": 44473,
            "vw": 10.9316,
            "o": 10.93,
            "c": 10.94,
            "h": 10.94,
            "l": 10.93,
            "t": 1710475200000,
            "n": 41
        },
        {
            "v": 376638,
            "vw": 10.9468,
            "o": 10.94,
            "c": 10.96,
            "h": 10.96,
            "l": 10.94,
            "t": 1710734400000,
            "n": 84
        },
        {
            "v": 60408,
            "vw": 10.9685,
            "o": 10.96,
            "c": 10.93,
            "h": 10.97,
            "l": 10.93,
            "t": 1710820800000,
            "n": 7
        },
        {
            "v": 1037,
            "vw": 10.9213,
            "o": 10.92,
            "c": 10.93,
            "h": 10.93,
            "l": 10.92,
            "t": 1710907200000,
            "n": 4
        },
        {
            "v": 13267,
            "vw": 10.9203,
            "o": 10.9206,
            "c": 10.92,
            "h": 10.925,
            "l": 10.92,
            "t": 1710993600000,
            "n": 14
        },
        {
            "v": 1623,
            "vw": 10.9499,
            "o": 10.96,
            "c": 10.94,
            "h": 10.96,
            "l": 10.94,
            "t": 1711080000000,
            "n": 10
        },
        {
            "v": 4266,
            "vw": 11.0048,
            "o": 10.94,
            "c": 10.935,
            "h": 10.9597,
            "l": 10.92,
            "t": 1712116800000,
            "n": 16
        },
        {
            "v": 6622,
            "vw": 11.0914,
            "o": 10.935,
            "c": 10.935,
            "h": 10.935,
            "l": 10.9202,
            "t": 1712203200000,
            "n": 165
        },
        {
            "v": 4365,
            "vw": 10.9336,
            "o": 10.95,
            "c": 10.945,
            "h": 10.95,
            "l": 10.935,
            "t": 1712289600000,
            "n": 23
        },
        {
            "v": 15287,
            "vw": 10.9792,
            "o": 10.98,
            "c": 10.95,
            "h": 10.98,
            "l": 10.95,
            "t": 1712548800000,
            "n": 26
        },
        {
            "v": 725,
            "vw": 11.0024,
            "o": 11.02,
            "c": 10.96,
            "h": 11.02,
            "l": 10.96,
            "t": 1712808000000,
            "n": 4
        },
        {
            "v": 50000,
            "vw": 10.97,
            "o": 10.97,
            "c": 10.97,
            "h": 10.97,
            "l": 10.97,
            "t": 1712894400000,
            "n": 1
        },
        {
            "v": 3215,
            "vw": 10.97,
            "o": 10.97,
            "c": 10.97,
            "h": 10.97,
            "l": 10.97,
            "t": 1713240000000,
            "n": 7
        },
        {
            "v": 752,
            "vw": 11.0093,
            "o": 11.0098,
            "c": 11.01,
            "h": 11.01,
            "l": 11.005,
            "t": 1713412800000,
            "n": 4
        },
        {
            "v": 50000,
            "vw": 11.01,
            "o": 11.01,
            "c": 11.01,
            "h": 11.01,
            "l": 11.01,
            "t": 1713758400000,
            "n": 1
        },
        {
            "v": 35100,
            "vw": 11.0103,
            "o": 11.02,
            "c": 11.01,
            "h": 11.02,
            "l": 11.01,
            "t": 1713844800000,
            "n": 27
        },
        {
            "v": 27570,
            "vw": 11.0102,
            "o": 11.01,
            "c": 11.01,
            "h": 11.01,
            "l": 11.01,
            "t": 1713931200000,
            "n": 13
        },
        {
            "v": 81338,
            "vw": 11.01,
            "o": 11.01,
            "c": 11.02,
            "h": 11.02,
            "l": 11.01,
            "t": 1714104000000,
            "n": 12
        },
        {
            "v": 5132,
            "vw": 11.02,
            "o": 11.02,
            "c": 11.02,
            "h": 11.02,
            "l": 11.02,
            "t": 1714536000000,
            "n": 4
        },
        {
            "v": 153,
            "vw": 11.02,
            "o": 11.02,
            "c": 11.02,
            "h": 11.02,
            "l": 11.02,
            "t": 1715227200000,
            "n": 2
        },
        {
            "v": 100,
            "vw": 11.02,
            "o": 11.02,
            "c": 11.02,
            "h": 11.02,
            "l": 11.02,
            "t": 1715313600000,
            "n": 1
        },
        {
            "v": 100,
            "vw": 11.02,
            "o": 11.02,
            "c": 11.02,
            "h": 11.02,
            "l": 11.02,
            "t": 1715572800000,
            "n": 1
        },
        {
            "v": 100,
            "vw": 11.03,
            "o": 11.03,
            "c": 11.03,
            "h": 11.03,
            "l": 11.03,
            "t": 1715745600000,
            "n": 1
        },
        {
            "v": 90435,
            "vw": 11.0455,
            "o": 11.04,
            "c": 11.04,
            "h": 11.15,
            "l": 11.04,
            "t": 1715832000000,
            "n": 116
        },
        {
            "v": 3048,
            "vw": 11.08,
            "o": 11.08,
            "c": 11.08,
            "h": 11.08,
            "l": 11.08,
            "t": 1715918400000,
            "n": 23
        },
        {
            "v": 1137,
            "vw": 11.7238,
            "o": 11.625,
            "c": 11.79,
            "h": 11.86,
            "l": 11.625,
            "t": 1716177600000,
            "n": 6
        },
        {
            "v": 1766,
            "vw": 11.0513,
            "o": 11.05,
            "c": 11.05,
            "h": 11.05,
            "l": 11.05,
            "t": 1716264000000,
            "n": 6
        },
        {
            "v": 186,
            "vw": 11.0359,
            "o": 11.04,
            "c": 11.04,
            "h": 11.04,
            "l": 11.04,
            "t": 1716350400000,
            "n": 5
        },
        {
            "v": 1255,
            "vw": 11.0333,
            "o": 11.03,
            "c": 11.04,
            "h": 11.04,
            "l": 11.03,
            "t": 1716523200000,
            "n": 2
        },
        {
            "v": 51150,
            "vw": 11.0498,
            "o": 11.05,
            "c": 11.055,
            "h": 11.055,
            "l": 11.045,
            "t": 1716955200000,
            "n": 46
        },
        {
            "v": 201,
            "vw": 11.055,
            "o": 11.06,
            "c": 11.06,
            "h": 11.06,
            "l": 11.06,
            "t": 1717387200000,
            "n": 3
        },
        {
            "v": 1510,
            "vw": 11.04,
            "o": 11.04,
            "c": 11.04,
            "h": 11.04,
            "l": 11.04,
            "t": 1717560000000,
            "n": 11
        },
        {
            "v": 152350,
            "vw": 11.05,
            "o": 11.05,
            "c": 11.05,
            "h": 11.05,
            "l": 11.05,
            "t": 1717646400000,
            "n": 3
        },
        {
            "v": 3313,
            "vw": 11.0497,
            "o": 11.05,
            "c": 11.04,
            "h": 11.05,
            "l": 11.04,
            "t": 1718164800000,
            "n": 15
        },
        {
            "v": 100,
            "vw": 11.05,
            "o": 11.05,
            "c": 11.05,
            "h": 11.05,
            "l": 11.05,
            "t": 1718337600000,
            "n": 1
        },
        {
            "v": 1628,
            "vw": 11.06,
            "o": 11.06,
            "c": 11.06,
            "h": 11.06,
            "l": 11.06,
            "t": 1718596800000,
            "n": 12
        },
        {
            "v": 2000,
            "vw": 11.07,
            "o": 11.07,
            "c": 11.07,
            "h": 11.07,
            "l": 11.07,
            "t": 1718942400000,
            "n": 6
        },
        {
            "v": 1013,
            "vw": 11.0753,
            "o": 11.08,
            "c": 11.07,
            "h": 11.08,
            "l": 11.07,
            "t": 1719201600000,
            "n": 6
        },
        {
            "v": 1002,
            "vw": 11.07,
            "o": 11.07,
            "c": 11.07,
            "h": 11.07,
            "l": 11.07,
            "t": 1719288000000,
            "n": 8
        },
        {
            "v": 101,
            "vw": 11.08,
            "o": 11.08,
            "c": 11.08,
            "h": 11.08,
            "l": 11.08,
            "t": 1720152000000,
            "n": 2
        },
        {
            "v": 50623,
            "vw": 11.08,
            "o": 11.08,
            "c": 11.08,
            "h": 11.08,
            "l": 11.08,
            "t": 1720411200000,
            "n": 43
        },
        {
            "v": 101,
            "vw": 11.06,
            "o": 11.06,
            "c": 11.06,
            "h": 11.06,
            "l": 11.06,
            "t": 1721102400000,
            "n": 2
        },
        {
            "v": 106725,
            "vw": 11.0747,
            "o": 11.06,
            "c": 11.07,
            "h": 11.1,
            "l": 11.05,
            "t": 1721188800000,
            "n": 88
        },
        {
            "v": 2301,
            "vw": 11.0898,
            "o": 11.09,
            "c": 11.085,
            "h": 11.09,
            "l": 11.085,
            "t": 1721275200000,
            "n": 11
        },
        {
            "v": 4618,
            "vw": 11.09,
            "o": 11.09,
            "c": 11.09,
            "h": 11.09,
            "l": 11.09,
            "t": 1721361600000,
            "n": 24
        },
        {
            "v": 1815,
            "vw": 11.1,
            "o": 11.1,
            "c": 11.1,
            "h": 11.1,
            "l": 11.1,
            "t": 1721620800000,
            "n": 11
        },
        {
            "v": 1402,
            "vw": 11.1103,
            "o": 11.11,
            "c": 11.11,
            "h": 11.12,
            "l": 11.105,
            "t": 1721793600000,
            "n": 11
        },
        {
            "v": 1239,
            "vw": 11.1199,
            "o": 11.12,
            "c": 11.12,
            "h": 11.12,
            "l": 11.12,
            "t": 1722225600000,
            "n": 11
        },
        {
            "v": 913,
            "vw": 11.12,
            "o": 11.12,
            "c": 11.12,
            "h": 11.12,
            "l": 11.12,
            "t": 1722398400000,
            "n": 4
        },
        {
            "v": 9576,
            "vw": 11.13,
            "o": 11.13,
            "c": 11.13,
            "h": 11.13,
            "l": 11.13,
            "t": 1722571200000,
            "n": 32
        },
        {
            "v": 338,
            "vw": 11.14,
            "o": 11.14,
            "c": 11.14,
            "h": 11.14,
            "l": 11.14,
            "t": 1722830400000,
            "n": 4
        },
        {
            "v": 1005,
            "vw": 11.14,
            "o": 11.14,
            "c": 11.14,
            "h": 11.14,
            "l": 11.14,
            "t": 1722916800000,
            "n": 6
        },
        {
            "v": 2911,
            "vw": 11.1457,
            "o": 11.14,
            "c": 11.15,
            "h": 11.15,
            "l": 11.14,
            "t": 1723003200000,
            "n": 16
        },
        {
            "v": 100101,
            "vw": 11.16,
            "o": 11.16,
            "c": 11.15,
            "h": 11.16,
            "l": 11.15,
            "t": 1723694400000,
            "n": 3
        },
        {
            "v": 1899,
            "vw": 11.1594,
            "o": 11.16,
            "c": 11.16,
            "h": 11.16,
            "l": 11.16,
            "t": 1724040000000,
            "n": 32
        },
        {
            "v": 552,
            "vw": 11.1781,
            "o": 11.16,
            "c": 11.16,
            "h": 11.16,
            "l": 11.16,
            "t": 1724385600000,
            "n": 11
        },
        {
            "v": 245,
            "vw": 11.1797,
            "o": 11.18,
            "c": 11.18,
            "h": 11.18,
            "l": 11.18,
            "t": 1724644800000,
            "n": 7
        },
        {
            "v": 150,
            "vw": 11.16,
            "o": 11.16,
            "c": 11.16,
            "h": 11.16,
            "l": 11.16,
            "t": 1724817600000,
            "n": 2
        },
        {
            "v": 4998,
            "vw": 11.2,
            "o": 11.2,
            "c": 11.2,
            "h": 11.2,
            "l": 11.2,
            "t": 1726459200000,
            "n": 11
        },
        {
            "v": 30004,
            "vw": 11.21,
            "o": 11.21,
            "c": 11.21,
            "h": 11.21,
            "l": 11.21,
            "t": 1727755200000,
            "n": 2
        },
        {
            "v": 1102,
            "vw": 11.22,
            "o": 11.22,
            "c": 11.22,
            "h": 11.22,
            "l": 11.22,
            "t": 1728014400000,
            "n": 3
        },
        {
            "v": 2604,
            "vw": 11.2262,
            "o": 11.22,
            "c": 11.23,
            "h": 11.23,
            "l": 11.22,
            "t": 1728273600000,
            "n": 13
        },
        {
            "v": 4184,
            "vw": 11.24,
            "o": 11.24,
            "c": 11.24,
            "h": 11.24,
            "l": 11.24,
            "t": 1728360000000,
            "n": 2
        },
        {
            "v": 1598,
            "vw": 11.2437,
            "o": 11.24,
            "c": 11.25,
            "h": 11.25,
            "l": 11.24,
            "t": 1728964800000,
            "n": 11
        },
        {
            "v": 1226,
            "vw": 11.24,
            "o": 11.24,
            "c": 11.24,
            "h": 11.24,
            "l": 11.24,
            "t": 1729051200000,
            "n": 5
        },
        {
            "v": 902,
            "vw": 11.299,
            "o": 11.3,
            "c": 11.3,
            "h": 11.3,
            "l": 11.3,
            "t": 1729828800000,
            "n": 8
        },
        {
            "v": 4414,
            "vw": 11.2916,
            "o": 11.26,
            "c": 11.28,
            "h": 11.3,
            "l": 11.26,
            "t": 1730088000000,
            "n": 16
        },
        {
            "v": 1878,
            "vw": 11.28,
            "o": 11.28,
            "c": 11.28,
            "h": 11.28,
            "l": 11.28,
            "t": 1730433600000,
            "n": 6
        },
        {
            "v": 14601,
            "vw": 11.3002,
            "o": 11.3,
            "c": 11.3,
            "h": 11.31,
            "l": 11.3,
            "t": 1730869200000,
            "n": 5
        },
        {
            "v": 357,
            "vw": 11.3096,
            "o": 11.31,
            "c": 11.31,
            "h": 11.31,
            "l": 11.31,
            "t": 1730955600000,
            "n": 6
        },
        {
            "v": 250032,
            "vw": 11.29,
            "o": 11.29,
            "c": 11.29,
            "h": 11.29,
            "l": 11.29,
            "t": 1731387600000,
            "n": 8
        },
        {
            "v": 205,
            "vw": 11.3003,
            "o": 11.3,
            "c": 11.3,
            "h": 11.3,
            "l": 11.3,
            "t": 1731906000000,
            "n": 5
        },
        {
            "v": 5396,
            "vw": 11.3002,
            "o": 11.3,
            "c": 11.3,
            "h": 11.3,
            "l": 11.3,
            "t": 1731992400000,
            "n": 7
        },
        {
            "v": 95114,
            "vw": 11.3,
            "o": 11.3,
            "c": 11.3,
            "h": 11.3,
            "l": 11.3,
            "t": 1732078800000,
            "n": 6
        },
        {
            "v": 169,
            "vw": 11.314,
            "o": 11.31,
            "c": 11.31,
            "h": 11.31,
            "l": 11.31,
            "t": 1732165200000,
            "n": 4
        },
        {
            "v": 301,
            "vw": 11.3083,
            "o": 11.31,
            "c": 11.31,
            "h": 11.31,
            "l": 11.305,
            "t": 1732251600000,
            "n": 4
        },
        {
            "v": 136,
            "vw": 11.3125,
            "o": 11.3101,
            "c": 11.3101,
            "h": 11.3101,
            "l": 11.3101,
            "t": 1732597200000,
            "n": 4
        },
        {
            "v": 1648,
            "vw": 11.3407,
            "o": 11.34,
            "c": 11.35,
            "h": 11.35,
            "l": 11.34,
            "t": 1733115600000,
            "n": 7
        },
        {
            "v": 302324,
            "vw": 11.3798,
            "o": 11.38,
            "c": 11.31,
            "h": 11.38,
            "l": 11.31,
            "t": 1733202000000,
            "n": 11
        },
        {
            "v": 370,
            "vw": 11.36,
            "o": 11.36,
            "c": 11.36,
            "h": 11.36,
            "l": 11.36,
            "t": 1733461200000,
            "n": 8
        },
        {
            "v": 71710,
            "vw": 11.36,
            "o": 11.36,
            "c": 11.36,
            "h": 11.36,
            "l": 11.36,
            "t": 1733720400000,
            "n": 4
        },
        {
            "v": 71204,
            "vw": 11.3798,
            "o": 11.36,
            "c": 11.38,
            "h": 11.38,
            "l": 11.36,
            "t": 1733806800000,
            "n": 8
        },
        {
            "v": 304,
            "vw": 11.34,
            "o": 11.34,
            "c": 11.34,
            "h": 11.34,
            "l": 11.34,
            "t": 1733979600000,
            "n": 3
        },
        {
            "v": 1102,
            "vw": 11.3527,
            "o": 11.38,
            "c": 11.35,
            "h": 11.38,
            "l": 11.35,
            "t": 1734411600000,
            "n": 5
        },
        {
            "v": 28261,
            "vw": 11.35,
            "o": 11.3087,
            "c": 11.35,
            "h": 11.35,
            "l": 11.3087,
            "t": 1735275600000,
            "n": 7
        },
        {
            "v": 476,
            "vw": 11.3697,
            "o": 11.38,
            "c": 11.341,
            "h": 11.38,
            "l": 11.341,
            "t": 1735794000000,
            "n": 8
        },
        {
            "v": 301,
            "vw": 11.3701,
            "o": 11.32,
            "c": 11.32,
            "h": 11.32,
            "l": 11.32,
            "t": 1736226000000,
            "n": 6
        },
        {
            "v": 2450,
            "vw": 11.4053,
            "o": 11.4,
            "c": 11.4,
            "h": 11.42,
            "l": 11.4,
            "t": 1737608400000,
            "n": 18
        },
        {
            "v": 122,
            "vw": 11.3533,
            "o": 11.34,
            "c": 11.34,
            "h": 11.34,
            "l": 11.34,
            "t": 1737694800000,
            "n": 3
        },
        {
            "v": 20946,
            "vw": 11.513,
            "o": 11.41,
            "c": 11.4212,
            "h": 11.57,
            "l": 11.39,
            "t": 1737954000000,
            "n": 112
        },
        {
            "v": 505,
            "vw": 11.54,
            "o": 11.54,
            "c": 11.54,
            "h": 11.54,
            "l": 11.54,
            "t": 1738040400000,
            "n": 7
        },
        {
            "v": 3872,
            "vw": 11.4784,
            "o": 11.55,
            "c": 11.5498,
            "h": 11.55,
            "l": 11.51,
            "t": 1739163600000,
            "n": 33
        },
        {
            "v": 102,
            "vw": 11.549,
            "o": 11.55,
            "c": 11.55,
            "h": 11.55,
            "l": 11.55,
            "t": 1739250000000,
            "n": 2
        },
        {
            "v": 3307,
            "vw": 11.4794,
            "o": 11.49,
            "c": 11.47,
            "h": 11.4983,
            "l": 11.47,
            "t": 1739336400000,
            "n": 37
        },
        {
            "v": 301,
            "vw": 11.4801,
            "o": 11.48,
            "c": 11.48,
            "h": 11.48,
            "l": 11.48,
            "t": 1739422800000,
            "n": 4
        },
        {
            "v": 1025,
            "vw": 11.5601,
            "o": 11.56,
            "c": 11.56,
            "h": 11.56,
            "l": 11.56,
            "t": 1739941200000,
            "n": 7
        },
        {
            "v": 5840,
            "vw": 11.5713,
            "o": 11.54,
            "c": 11.58,
            "h": 11.58,
            "l": 11.54,
            "t": 1740632400000,
            "n": 17
        },
        {
            "v": 23298,
            "vw": 11.5929,
            "o": 11.59,
            "c": 11.62,
            "h": 11.62,
            "l": 11.59,
            "t": 1740718800000,
            "n": 67
        },
        {
            "v": 15974,
            "vw": 11.6,
            "o": 11.6,
            "c": 11.6,
            "h": 11.6,
            "l": 11.6,
            "t": 1740978000000,
            "n": 80
        },
        {
            "v": 120,
            "vw": 11.6094,
            "o": 11.61,
            "c": 11.61,
            "h": 11.61,
            "l": 11.61,
            "t": 1741064400000,
            "n": 6
        },
        {
            "v": 7951,
            "vw": 11.6193,
            "o": 11.61,
            "c": 11.65,
            "h": 11.65,
            "l": 11.61,
            "t": 1741323600000,
            "n": 14
        },
        {
            "v": 2914,
            "vw": 11.6234,
            "o": 11.64,
            "c": 11.6,
            "h": 11.64,
            "l": 11.6,
            "t": 1741579200000,
            "n": 25
        },
        {
            "v": 1250,
            "vw": 11.6412,
            "o": 11.64,
            "c": 11.65,
            "h": 11.65,
            "l": 11.64,
            "t": 1741752000000,
            "n": 5
        },
        {
            "v": 336,
            "vw": 11.6387,
            "o": 11.65,
            "c": 11.6119,
            "h": 11.65,
            "l": 11.6119,
            "t": 1741838400000,
            "n": 13
        },
        {
            "v": 1038,
            "vw": 11.6003,
            "o": 11.6,
            "c": 11.6,
            "h": 11.6,
            "l": 11.6,
            "t": 1741924800000,
            "n": 8
        },
        {
            "v": 308,
            "vw": 11.6043,
            "o": 11.6,
            "c": 11.61,
            "h": 11.61,
            "l": 11.6,
            "t": 1742788800000,
            "n": 5
        },
        {
            "v": 1935,
            "vw": 11.6102,
            "o": 11.61,
            "c": 11.61,
            "h": 11.61,
            "l": 11.61,
            "t": 1742875200000,
            "n": 12
        },
        {
            "v": 4067,
            "vw": 11.6662,
            "o": 11.71,
            "c": 11.62,
            "h": 11.72,
            "l": 11.62,
            "t": 1745553600000,
            "n": 30
        },
        {
            "v": 25955,
            "vw": 11.7208,
            "o": 11.72,
            "c": 11.7,
            "h": 11.75,
            "l": 11.7,
            "t": 1746590400000,
            "n": 12
        },
        {
            "v": 202,
            "vw": 11.6996,
            "o": 11.7,
            "c": 11.7,
            "h": 11.7,
            "l": 11.7,
            "t": 1747627200000,
            "n": 2
        },
        {
            "v": 122,
            "vw": 11.8163,
            "o": 11.82,
            "c": 11.82,
            "h": 11.82,
            "l": 11.82,
            "t": 1747713600000,
            "n": 6
        },
        {
            "v": 1328,
            "vw": 11.7002,
            "o": 11.7,
            "c": 11.7,
            "h": 11.7,
            "l": 11.7,
            "t": 1748404800000,
            "n": 3
        },
        {
            "v": 225,
            "vw": 11.71,
            "o": 11.71,
            "c": 11.71,
            "h": 11.71,
            "l": 11.71,
            "t": 1749614400000,
            "n": 2
        },
        {
            "v": 271,
            "vw": 11.7853,
            "o": 11.79,
            "c": 11.79,
            "h": 11.79,
            "l": 11.79,
            "t": 1750219200000,
            "n": 28
        },
        {
            "v": 192,
            "vw": 11.7943,
            "o": 11.8,
            "c": 11.8,
            "h": 11.8,
            "l": 11.8,
            "t": 1750392000000,
            "n": 19
        },
        {
            "v": 3504,
            "vw": 11.8044,
            "o": 11.77,
            "c": 11.81,
            "h": 11.81,
            "l": 11.77,
            "t": 1750651200000,
            "n": 10
        },
        {
            "v": 100,
            "vw": 11.8,
            "o": 11.8,
            "c": 11.8,
            "h": 11.8,
            "l": 11.8,
            "t": 1750737600000,
            "n": 1
        },
        {
            "v": 101,
            "vw": 11.8387,
            "o": 11.84,
            "c": 11.84,
            "h": 11.84,
            "l": 11.84,
            "t": 1751342400000,
            "n": 2
        }
    ],
    "status": "DELAYED",
    "request_id": "89aac1bddd98af1796dbe9a4a56fe75e",
    "count": 206
}