{
    "ticker": "BZAI",
    "queryCount": 118,
    "resultsCount": 118,
    "adjusted": true,
    "results": [
        {
            "v": 167293,
            "vw": 14.3681,
            "o": 17.5,
            "c": 13.09,
            "h": 19.25,
            "l": 12.15,
            "t": 1736830800000,
            "n": 2285
        },
        {
            "v": 400585,
            "vw": 11.0165,
            "o": 13.5,
            "c": 9.6,
            "h": 13.63,
            "l": 9.51,
            "t": 1736917200000,
            "n": 4452
        },
        {
            "v": 579505,
            "vw": 7.3959,
            "o": 10.07,
            "c": 6.5,
            "h": 10.5,
            "l": 6.2,
            "t": 1737003600000,
            "n": 6091
        },
        {
            "v": 2194490.0,
            "vw": 9.1143,
            "o": 7.69,
            "c": 8.29,
            "h": 11.5,
            "l": 7.5,
            "t": 1737090000000,
            "n": 20887
        },
        {
            "v": 392437,
            "vw": 7.7305,
            "o": 8.18,
            "c": 7.56,
            "h": 8.7,
            "l": 7.2,
            "t": 1737435600000,
            "n": 3125
        },
        {
            "v": 376606,
            "vw": 7.0243,
            "o": 7.85,
            "c": 6.32,
            "h": 8.1,
            "l": 6.26,
            "t": 1737522000000,
            "n": 3409
        },
        {
            "v": 236893,
            "vw": 6.8547,
            "o": 7.33,
            "c": 6.72,
            "h": 7.33,
            "l": 6.5,
            "t": 1737608400000,
            "n": 1815
        },
        {
            "v": 296735,
            "vw": 6.9066,
            "o": 6.99,
            "c": 6.53,
            "h": 7.49,
            "l": 6.4,
            "t": 1737694800000,
            "n": 1811
        },
        {
            "v": 358329,
            "vw": 5.8291,
            "o": 6,
            "c": 5.15,
            "h": 6.5,
            "l": 5.09,
            "t": 1737954000000,
            "n": 2053
        },
        {
            "v": 411542,
            "vw": 5.5976,
            "o": 5.65,
            "c": 5.61,
            "h": 5.9,
            "l": 5.1,
            "t": 1738040400000,
            "n": 5374
        },
        {
            "v": 233449,
            "vw": 5.8342,
            "o": 5.9,
            "c": 5.99,
            "h": 6,
            "l": 5.62,
            "t": 1738126800000,
            "n": 2605
        },
        {
            "v": 347131,
            "vw": 6.1386,
            "o": 6.25,
            "c": 5.72,
            "h": 6.4,
            "l": 5.6,
            "t": 1738213200000,
            "n": 2888
        },
        {
            "v": 118268,
            "vw": 5.9785,
            "o": 5.81,
            "c": 6,
            "h": 6.0695,
            "l": 5.81,
            "t": 1738299600000,
            "n": 1111
        },
        {
            "v": 179251,
            "vw": 5.886,
            "o": 5.71,
            "c": 5.93,
            "h": 6.03,
            "l": 5.6,
            "t": 1738558800000,
            "n": 1510
        },
        {
            "v": 285623,
            "vw": 5.949,
            "o": 5.95,
            "c": 5.86,
            "h": 6.0494,
            "l": 5.7,
            "t": 1738645200000,
            "n": 2473
        },
        {
            "v": 252155,
            "vw": 5.8239,
            "o": 5.83,
            "c": 5.675,
            "h": 6,
            "l": 5.6,
            "t": 1738731600000,
            "n": 2031
        },
        {
            "v": 352173,
            "vw": 5.3907,
            "o": 5.6,
            "c": 5.3,
            "h": 5.855,
            "l": 5.09,
            "t": 1738818000000,
            "n": 1815
        },
        {
            "v": 588553,
            "vw": 4.7136,
            "o": 5.31,
            "c": 4.67,
            "h": 5.31,
            "l": 4.4,
            "t": 1738904400000,
            "n": 4072
        },
        {
            "v": 1066821.0,
            "vw": 3.9929,
            "o": 5,
            "c": 3.44,
            "h": 5.25,
            "l": 3.25,
            "t": 1739163600000,
            "n": 6423
        },
        {
            "v": 768628,
            "vw": 3.4811,
            "o": 3.6,
            "c": 3.21,
            "h": 3.9,
            "l": 3.21,
            "t": 1739250000000,
            "n": 4839
        },
        {
            "v": 2090193.0,
            "vw": 3.1936,
            "o": 3.74,
            "c": 3.05,
            "h": 3.74,
            "l": 2.85,
            "t": 1739336400000,
            "n": 12331
        },
        {
            "v": 3433796.0,
            "vw": 4.0438,
            "o": 3.2,
            "c": 4,
            "h": 4.54,
            "l": 3.14,
            "t": 1739422800000,
            "n": 18673
        },
        {
            "v": 4199892.0,
            "vw": 4.8466,
            "o": 4.31,
            "c": 5.15,
            "h": 5.49,
            "l": 3.9,
            "t": 1739509200000,
            "n": 17054
        },
        {
            "v": 2384687.0,
            "vw": 4.9208,
            "o": 5.23,
            "c": 4.31,
            "h": 5.6499,
            "l": 4.28,
            "t": 1739854800000,
            "n": 13088
        },
        {
            "v": 930838,
            "vw": 4.331,
            "o": 4.5,
            "c": 4.49,
            "h": 4.63,
            "l": 4.12,
            "t": 1739941200000,
            "n": 5606
        },
        {
            "v": 858813,
            "vw": 4.215,
            "o": 4.5,
            "c": 4.21,
            "h": 4.51,
            "l": 4.02,
            "t": 1740027600000,
            "n": 5908
        },
        {
            "v": 818441,
            "vw": 4.1258,
            "o": 4.26,
            "c": 4.09,
            "h": 4.445,
            "l": 4,
            "t": 1740114000000,
            "n": 6342
        },
        {
            "v": 704964,
            "vw": 3.7968,
            "o": 4.05,
            "c": 3.71,
            "h": 4.19,
            "l": 3.6,
            "t": 1740373200000,
            "n": 4425
        },
        {
            "v": 448720,
            "vw": 3.7202,
            "o": 3.68,
            "c": 3.73,
            "h": 3.875,
            "l": 3.6,
            "t": 1740459600000,
            "n": 4047
        },
        {
            "v": 310978,
            "vw": 3.7016,
            "o": 3.83,
            "c": 3.63,
            "h": 3.875,
            "l": 3.57,
            "t": 1740546000000,
            "n": 2012
        },
        {
            "v": 288160,
            "vw": 3.5656,
            "o": 3.65,
            "c": 3.56,
            "h": 3.7399,
            "l": 3.4501,
            "t": 1740632400000,
            "n": 3440
        },
        {
            "v": 803152,
            "vw": 3.1764,
            "o": 3.51,
            "c": 3.06,
            "h": 3.6613,
            "l": 2.96,
            "t": 1740718800000,
            "n": 7608
        },
        {
            "v": 580076,
            "vw": 3.0861,
            "o": 3.09,
            "c": 2.94,
            "h": 3.48,
            "l": 2.8,
            "t": 1740978000000,
            "n": 4539
        },
        {
            "v": 738474,
            "vw": 3.2467,
            "o": 2.94,
            "c": 3.37,
            "h": 3.58,
            "l": 2.745,
            "t": 1741064400000,
            "n": 5355
        },
        {
            "v": 344221,
            "vw": 3.2505,
            "o": 3.5,
            "c": 3.23,
            "h": 3.5,
            "l": 3.15,
            "t": 1741150800000,
            "n": 3032
        },
        {
            "v": 290006,
            "vw": 3.1889,
            "o": 3.28,
            "c": 3.1,
            "h": 3.4,
            "l": 3.06,
            "t": 1741237200000,
            "n": 3048
        },
        {
            "v": 425160,
            "vw": 3.2313,
            "o": 3.06,
            "c": 3.3,
            "h": 3.4899,
            "l": 3.06,
            "t": 1741323600000,
            "n": 4239
        },
        {
            "v": 708972,
            "vw": 3.1843,
            "o": 3.4,
            "c": 3.16,
            "h": 3.5,
            "l": 3.01,
            "t": 1741579200000,
            "n": 6173
        },
        {
            "v": 719661,
            "vw": 3.3299,
            "o": 3.06,
            "c": 3.38,
            "h": 3.47,
            "l": 3.06,
            "t": 1741665600000,
            "n": 5720
        },
        {
            "v": 637615,
            "vw": 3.5043,
            "o": 3.46,
            "c": 3.31,
            "h": 3.7578,
            "l": 3.29,
            "t": 1741752000000,
            "n": 5649
        },
        {
            "v": 1039569.0,
            "vw": 3.4704,
            "o": 3.27,
            "c": 3.49,
            "h": 3.74,
            "l": 3.17,
            "t": 1741838400000,
            "n": 6765
        },
        {
            "v": 1613385.0,
            "vw": 3.6974,
            "o": 3.68,
            "c": 3.52,
            "h": 4.08,
            "l": 3.3,
            "t": 1741924800000,
            "n": 7213
        },
        {
            "v": 677971,
            "vw": 3.5207,
            "o": 3.5,
            "c": 3.36,
            "h": 3.8,
            "l": 3.31,
            "t": 1742184000000,
            "n": 6811
        },
        {
            "v": 552937,
            "vw": 3.3078,
            "o": 3.33,
            "c": 3.24,
            "h": 3.45,
            "l": 3.15,
            "t": 1742270400000,
            "n": 5072
        },
        {
            "v": 788612,
            "vw": 3.3215,
            "o": 3.43,
            "c": 3.34,
            "h": 3.45,
            "l": 3.2,
            "t": 1742356800000,
            "n": 7513
        },
        {
            "v": 1159905.0,
            "vw": 3.3549,
            "o": 3.29,
            "c": 3.27,
            "h": 3.5196,
            "l": 3.205,
            "t": 1742443200000,
            "n": 6267
        },
        {
            "v": 3919422.0,
            "vw": 3.3063,
            "o": 3.25,
            "c": 3.32,
            "h": 3.41,
            "l": 3.06,
            "t": 1742529600000,
            "n": 7809
        },
        {
            "v": 707251,
            "vw": 3.1652,
            "o": 3.35,
            "c": 3.18,
            "h": 3.35,
            "l": 3.05,
            "t": 1742788800000,
            "n": 4260
        },
        {
            "v": 707031,
            "vw": 3.2524,
            "o": 3.23,
            "c": 3.12,
            "h": 3.4399,
            "l": 3.1,
            "t": 1742875200000,
            "n": 4627
        },
        {
            "v": 874225,
            "vw": 2.8825,
            "o": 3.12,
            "c": 2.76,
            "h": 3.1706,
            "l": 2.7,
            "t": 1742961600000,
            "n": 6809
        },
        {
            "v": 384414,
            "vw": 2.7579,
            "o": 2.76,
            "c": 2.78,
            "h": 2.8888,
            "l": 2.7,
            "t": 1743048000000,
            "n": 2182
        },
        {
            "v": 918853,
            "vw": 2.3873,
            "o": 2.76,
            "c": 2.305,
            "h": 2.81,
            "l": 2.3,
            "t": 1743134400000,
            "n": 3462
        },
        {
            "v": 1046553.0,
            "vw": 1.9289,
            "o": 2.27,
            "c": 2.02,
            "h": 2.455,
            "l": 1.7,
            "t": 1743393600000,
            "n": 8112
        },
        {
            "v": 724898,
            "vw": 2.1743,
            "o": 2.04,
            "c": 2.19,
            "h": 2.41,
            "l": 2.02,
            "t": 1743480000000,
            "n": 4502
        },
        {
            "v": 251955,
            "vw": 2.175,
            "o": 2.12,
            "c": 2.2,
            "h": 2.28,
            "l": 2.06,
            "t": 1743566400000,
            "n": 1994
        },
        {
            "v": 250719,
            "vw": 2.0262,
            "o": 2.11,
            "c": 2.04,
            "h": 2.12,
            "l": 1.96,
            "t": 1743652800000,
            "n": 1647
        },
        {
            "v": 375242,
            "vw": 2.1425,
            "o": 2.05,
            "c": 2.23,
            "h": 2.29,
            "l": 1.95,
            "t": 1743739200000,
            "n": 2988
        },
        {
            "v": 495112,
            "vw": 2.4367,
            "o": 2.1,
            "c": 2.51,
            "h": 2.53,
            "l": 2.08,
            "t": 1743998400000,
            "n": 3923
        },
        {
            "v": 261486,
            "vw": 2.4533,
            "o": 2.74,
            "c": 2.35,
            "h": 2.74,
            "l": 2.33,
            "t": 1744084800000,
            "n": 2024
        },
        {
            "v": 377418,
            "vw": 2.4662,
            "o": 2.29,
            "c": 2.64,
            "h": 2.69,
            "l": 2.225,
            "t": 1744171200000,
            "n": 3758
        },
        {
            "v": 239751,
            "vw": 2.4803,
            "o": 2.58,
            "c": 2.48,
            "h": 2.61,
            "l": 2.39,
            "t": 1744257600000,
            "n": 1841
        },
        {
            "v": 436497,
            "vw": 2.5263,
            "o": 2.48,
            "c": 2.6,
            "h": 2.64,
            "l": 2.25,
            "t": 1744344000000,
            "n": 2967
        },
        {
            "v": 339574,
            "vw": 2.8015,
            "o": 2.6,
            "c": 2.91,
            "h": 2.99,
            "l": 2.49,
            "t": 1744603200000,
            "n": 2772
        },
        {
            "v": 379063,
            "vw": 2.9832,
            "o": 2.91,
            "c": 3.07,
            "h": 3.1,
            "l": 2.81,
            "t": 1744689600000,
            "n": 3475
        },
        {
            "v": 312318,
            "vw": 2.9842,
            "o": 2.94,
            "c": 2.81,
            "h": 3.255,
            "l": 2.77,
            "t": 1744776000000,
            "n": 3573
        },
        {
            "v": 142201,
            "vw": 2.7342,
            "o": 2.8,
            "c": 2.77,
            "h": 2.9,
            "l": 2.635,
            "t": 1744862400000,
            "n": 2254
        },
        {
            "v": 255180,
            "vw": 2.7963,
            "o": 2.69,
            "c": 2.67,
            "h": 3.025,
            "l": 2.66,
            "t": 1745208000000,
            "n": 3260
        },
        {
            "v": 399022,
            "vw": 2.5132,
            "o": 2.65,
            "c": 2.47,
            "h": 2.74,
            "l": 2.4,
            "t": 1745294400000,
            "n": 3588
        },
        {
            "v": 139609,
            "vw": 2.5372,
            "o": 2.59,
            "c": 2.51,
            "h": 2.6299,
            "l": 2.4725,
            "t": 1745380800000,
            "n": 1811
        },
        {
            "v": 245562,
            "vw": 2.6373,
            "o": 2.63,
            "c": 2.64,
            "h": 2.71,
            "l": 2.49,
            "t": 1745467200000,
            "n": 2564
        },
        {
            "v": 210647,
            "vw": 2.5403,
            "o": 2.58,
            "c": 2.56,
            "h": 2.63,
            "l": 2.43,
            "t": 1745553600000,
            "n": 1769
        },
        {
            "v": 196814,
            "vw": 2.4379,
            "o": 2.55,
            "c": 2.4,
            "h": 2.61,
            "l": 2.36,
            "t": 1745812800000,
            "n": 2093
        },
        {
            "v": 150291,
            "vw": 2.3809,
            "o": 2.39,
            "c": 2.38,
            "h": 2.53,
            "l": 2.31,
            "t": 1745899200000,
            "n": 1465
        },
        {
            "v": 249527,
            "vw": 2.3881,
            "o": 2.35,
            "c": 2.42,
            "h": 2.5,
            "l": 2.26,
            "t": 1745985600000,
            "n": 2442
        },
        {
            "v": 132219,
            "vw": 2.4513,
            "o": 2.37,
            "c": 2.46,
            "h": 2.53,
            "l": 2.33,
            "t": 1746072000000,
            "n": 1338
        },
        {
            "v": 207894,
            "vw": 2.6509,
            "o": 2.43,
            "c": 2.69,
            "h": 2.73,
            "l": 2.43,
            "t": 1746158400000,
            "n": 1864
        },
        {
            "v": 184882,
            "vw": 2.6579,
            "o": 2.63,
            "c": 2.62,
            "h": 2.79,
            "l": 2.55,
            "t": 1746417600000,
            "n": 1338
        },
        {
            "v": 149223,
            "vw": 2.5539,
            "o": 2.65,
            "c": 2.62,
            "h": 2.68,
            "l": 2.46,
            "t": 1746504000000,
            "n": 882
        },
        {
            "v": 116977,
            "vw": 2.5326,
            "o": 2.57,
            "c": 2.52,
            "h": 2.65,
            "l": 2.49,
            "t": 1746590400000,
            "n": 1102
        },
        {
            "v": 159544,
            "vw": 2.5136,
            "o": 2.52,
            "c": 2.48,
            "h": 2.6,
            "l": 2.41,
            "t": 1746676800000,
            "n": 2058
        },
        {
            "v": 164137,
            "vw": 2.4361,
            "o": 2.5,
            "c": 2.44,
            "h": 2.563,
            "l": 2.35,
            "t": 1746763200000,
            "n": 1573
        },
        {
            "v": 455250,
            "vw": 2.7061,
            "o": 2.58,
            "c": 2.72,
            "h": 2.74,
            "l": 2.57,
            "t": 1747022400000,
            "n": 3998
        },
        {
            "v": 328335,
            "vw": 2.8625,
            "o": 2.71,
            "c": 2.83,
            "h": 3,
            "l": 2.62,
            "t": 1747108800000,
            "n": 3081
        },
        {
            "v": 289985,
            "vw": 2.8615,
            "o": 2.84,
            "c": 2.78,
            "h": 3,
            "l": 2.755,
            "t": 1747195200000,
            "n": 2214
        },
        {
            "v": 685515,
            "vw": 2.369,
            "o": 2.75,
            "c": 2.17,
            "h": 2.81,
            "l": 2.17,
            "t": 1747281600000,
            "n": 2487
        },
        {
            "v": 466167,
            "vw": 2.1593,
            "o": 2.26,
            "c": 2.13,
            "h": 2.345,
            "l": 2.055,
            "t": 1747368000000,
            "n": 2059
        },
        {
            "v": 264245,
            "vw": 2.0322,
            "o": 2.13,
            "c": 2.1,
            "h": 2.16,
            "l": 1.91,
            "t": 1747627200000,
            "n": 1739
        },
        {
            "v": 592028,
            "vw": 2.2709,
            "o": 2.08,
            "c": 2.2,
            "h": 2.48,
            "l": 2.02,
            "t": 1747713600000,
            "n": 3172
        },
        {
            "v": 341659,
            "vw": 2.2541,
            "o": 2.29,
            "c": 2.19,
            "h": 2.39,
            "l": 2.1,
            "t": 1747800000000,
            "n": 1889
        },
        {
            "v": 704211,
            "vw": 2.4693,
            "o": 2.16,
            "c": 2.45,
            "h": 2.6,
            "l": 2.16,
            "t": 1747886400000,
            "n": 3585
        },
        {
            "v": 332078,
            "vw": 2.3937,
            "o": 2.4,
            "c": 2.3,
            "h": 2.52,
            "l": 2.29,
            "t": 1747972800000,
            "n": 2245
        },
        {
            "v": 669973,
            "vw": 2.108,
            "o": 2.35,
            "c": 2.03,
            "h": 2.35,
            "l": 2,
            "t": 1748318400000,
            "n": 2968
        },
        {
            "v": 326661,
            "vw": 2.0282,
            "o": 2.06,
            "c": 2.03,
            "h": 2.1157,
            "l": 1.97,
            "t": 1748404800000,
            "n": 1515
        },
        {
            "v": 202663,
            "vw": 2.0329,
            "o": 2.04,
            "c": 2.02,
            "h": 2.1099,
            "l": 2,
            "t": 1748491200000,
            "n": 2429
        },
        {
            "v": 267759,
            "vw": 1.9831,
            "o": 2.03,
            "c": 2.01,
            "h": 2.0656,
            "l": 1.93,
            "t": 1748577600000,
            "n": 1585
        },
        {
            "v": 264750,
            "vw": 2.027,
            "o": 2.03,
            "c": 2.03,
            "h": 2.07,
            "l": 1.9528,
            "t": 1748836800000,
            "n": 2630
        },
        {
            "v": 297997,
            "vw": 2.1306,
            "o": 2.06,
            "c": 2.14,
            "h": 2.23,
            "l": 2,
            "t": 1748923200000,
            "n": 1795
        },
        {
            "v": 347482,
            "vw": 2.3225,
            "o": 2.12,
            "c": 2.48,
            "h": 2.5,
            "l": 2.09,
            "t": 1749009600000,
            "n": 2026
        },
        {
            "v": 323123,
            "vw": 2.5393,
            "o": 2.45,
            "c": 2.6,
            "h": 2.66,
            "l": 2.4,
            "t": 1749096000000,
            "n": 2206
        },
        {
            "v": 301209,
            "vw": 2.6416,
            "o": 2.65,
            "c": 2.55,
            "h": 2.75,
            "l": 2.54,
            "t": 1749182400000,
            "n": 1764
        },
        {
            "v": 208600,
            "vw": 2.513,
            "o": 2.52,
            "c": 2.45,
            "h": 2.6576,
            "l": 2.43,
            "t": 1749441600000,
            "n": 1635
        },
        {
            "v": 355360,
            "vw": 2.4561,
            "o": 2.45,
            "c": 2.52,
            "h": 2.54,
            "l": 2.33,
            "t": 1749528000000,
            "n": 2473
        },
        {
            "v": 352560,
            "vw": 2.5043,
            "o": 2.54,
            "c": 2.52,
            "h": 2.58,
            "l": 2.41,
            "t": 1749614400000,
            "n": 2318
        },
        {
            "v": 148399,
            "vw": 2.4428,
            "o": 2.48,
            "c": 2.43,
            "h": 2.53,
            "l": 2.38,
            "t": 1749700800000,
            "n": 2484
        },
        {
            "v": 170134,
            "vw": 2.3521,
            "o": 2.38,
            "c": 2.35,
            "h": 2.51,
            "l": 2.25,
            "t": 1749787200000,
            "n": 1574
        },
        {
            "v": 211694,
            "vw": 2.4517,
            "o": 2.36,
            "c": 2.44,
            "h": 2.52,
            "l": 2.2804,
            "t": 1750046400000,
            "n": 2106
        },
        {
            "v": 178956,
            "vw": 2.4902,
            "o": 2.53,
            "c": 2.46,
            "h": 2.579,
            "l": 2.43,
            "t": 1750132800000,
            "n": 1267
        },
        {
            "v": 299485,
            "vw": 2.5851,
            "o": 2.44,
            "c": 2.58,
            "h": 2.6866,
            "l": 2.4229,
            "t": 1750219200000,
            "n": 2326
        },
        {
            "v": 519022,
            "vw": 2.7136,
            "o": 2.58,
            "c": 2.71,
            "h": 2.8,
            "l": 2.54,
            "t": 1750392000000,
            "n": 2858
        },
        {
            "v": 538691,
            "vw": 2.5776,
            "o": 2.75,
            "c": 2.41,
            "h": 2.8346,
            "l": 2.4025,
            "t": 1750651200000,
            "n": 2799
        },
        {
            "v": 248962,
            "vw": 2.5259,
            "o": 2.48,
            "c": 2.57,
            "h": 2.61,
            "l": 2.34,
            "t": 1750737600000,
            "n": 1993
        },
        {
            "v": 219532,
            "vw": 2.4986,
            "o": 2.55,
            "c": 2.55,
            "h": 2.64,
            "l": 2.41,
            "t": 1750824000000,
            "n": 1990
        },
        {
            "v": 245027,
            "vw": 2.6872,
            "o": 2.55,
            "c": 2.73,
            "h": 2.77,
            "l": 2.5,
            "t": 1750910400000,
            "n": 2669
        },
        {
            "v": 518673,
            "vw": 2.4452,
            "o": 2.7,
            "c": 2.35,
            "h": 2.73,
            "l": 2.35,
            "t": 1750996800000,
            "n": 2480
        },
        {
            "v": 1746636.0,
            "vw": 2.9094,
            "o": 2.63,
            "c": 2.98,
            "h": 3,
            "l": 2.53,
            "t": 1751256000000,
            "n": 6552
        },
        {
            "v": 987739,
            "vw": 3.0294,
            "o": 3,
            "c": 2.93,
            "h": 3.005,
            "l": 2.76,
            "t": 1751342400000,
            "n": 6130
        },
        {
            "v": 640826,
            "vw": 2.9764,
            "o": 2.95,
            "c": 2.99,
            "h": 3.06,
            "l": 2.85,
            "t": 1751428800000,
            "n": 3468
        },
        {
            "v": 326003,
            "vw": 2.9253,
            "o": 3.04,
            "c": 2.82,
            "h": 3.05,
            "l": 2.78,
            "t": 1751515200000,
            "n": 1671
        }
    ],
    "status": "DELAYED",
    "request_id": "fbb3b68333a122979603c96a0e75130a",
    "count": 118
}