{
    "ticker": "DMAAR",
    "queryCount": 64,
    "resultsCount": 64,
    "adjusted": true,
    "results": [
        {
            "v": 3961568.0,
            "vw": 0.1564,
            "o": 0.16,
            "c": 0.151,
            "h": 0.165,
            "l": 0.15,
            "t": 1740459600000,
            "n": 266
        },
        {
            "v": 133655,
            "vw": 0.1502,
            "o": 0.151,
            "c": 0.15,
            "h": 0.1511,
            "l": 0.15,
            "t": 1740546000000,
            "n": 89
        },
        {
            "v": 89804,
            "vw": 0.1501,
            "o": 0.1536,
            "c": 0.15,
            "h": 0.155,
            "l": 0.15,
            "t": 1740632400000,
            "n": 56
        },
        {
            "v": 997908,
            "vw": 0.15,
            "o": 0.1521,
            "c": 0.15,
            "h": 0.1521,
            "l": 0.145,
            "t": 1740718800000,
            "n": 53
        },
        {
            "v": 10000,
            "vw": 0.1402,
            "o": 0.14,
            "c": 0.14,
            "h": 0.145,
            "l": 0.14,
            "t": 1740978000000,
            "n": 14
        },
        {
            "v": 300000,
            "vw": 0.15,
            "o": 0.15,
            "c": 0.15,
            "h": 0.15,
            "l": 0.15,
            "t": 1741064400000,
            "n": 1
        },
        {
            "v": 53700,
            "vw": 0.1496,
            "o": 0.152,
            "c": 0.1486,
            "h": 0.1521,
            "l": 0.14,
            "t": 1741150800000,
            "n": 81
        },
        {
            "v": 833,
            "vw": 0.146,
            "o": 0.14,
            "c": 0.15,
            "h": 0.15,
            "l": 0.14,
            "t": 1741237200000,
            "n": 6
        },
        {
            "v": 217,
            "vw": 0.1347,
            "o": 0.14,
            "c": 0.14,
            "h": 0.14,
            "l": 0.14,
            "t": 1741323600000,
            "n": 3
        },
        {
            "v": 26200,
            "vw": 0.1399,
            "o": 0.1373,
            "c": 0.14,
            "h": 0.142,
            "l": 0.1342,
            "t": 1741579200000,
            "n": 88
        },
        {
            "v": 532527,
            "vw": 0.1398,
            "o": 0.14,
            "c": 0.1395,
            "h": 0.14,
            "l": 0.13,
            "t": 1741838400000,
            "n": 34
        },
        {
            "v": 364,
            "vw": 0.14,
            "o": 0.14,
            "c": 0.14,
            "h": 0.14,
            "l": 0.14,
            "t": 1741924800000,
            "n": 1
        },
        {
            "v": 500000,
            "vw": 0.14,
            "o": 0.14,
            "c": 0.14,
            "h": 0.14,
            "l": 0.14,
            "t": 1742184000000,
            "n": 1
        },
        {
            "v": 372,
            "vw": 0.14,
            "o": 0.14,
            "c": 0.14,
            "h": 0.14,
            "l": 0.14,
            "t": 1742356800000,
            "n": 10
        },
        {
            "v": 1362,
            "vw": 0.1217,
            "o": 0.116,
            "c": 0.14,
            "h": 0.14,
            "l": 0.1159,
            "t": 1742529600000,
            "n": 26
        },
        {
            "v": 3359,
            "vw": 0.1309,
            "o": 0.14,
            "c": 0.13,
            "h": 0.14,
            "l": 0.13,
            "t": 1742788800000,
            "n": 7
        },
        {
            "v": 32153,
            "vw": 0.1298,
            "o": 0.1281,
            "c": 0.13,
            "h": 0.1301,
            "l": 0.1281,
            "t": 1742875200000,
            "n": 178
        },
        {
            "v": 665,
            "vw": 0.1254,
            "o": 0.13,
            "c": 0.1202,
            "h": 0.13,
            "l": 0.1202,
            "t": 1742961600000,
            "n": 3
        },
        {
            "v": 34124,
            "vw": 0.1294,
            "o": 0.1201,
            "c": 0.13,
            "h": 0.13,
            "l": 0.1201,
            "t": 1743048000000,
            "n": 101
        },
        {
            "v": 13868,
            "vw": 0.1312,
            "o": 0.1246,
            "c": 0.14,
            "h": 0.14,
            "l": 0.1011,
            "t": 1743134400000,
            "n": 33
        },
        {
            "v": 10669,
            "vw": 0.1306,
            "o": 0.14,
            "c": 0.13,
            "h": 0.14,
            "l": 0.13,
            "t": 1743393600000,
            "n": 62
        },
        {
            "v": 432,
            "vw": 0.1343,
            "o": 0.14,
            "c": 0.14,
            "h": 0.14,
            "l": 0.14,
            "t": 1743566400000,
            "n": 12
        },
        {
            "v": 7052,
            "vw": 0.1017,
            "o": 0.110051,
            "c": 0.1246,
            "h": 0.1246,
            "l": 0.0902,
            "t": 1743652800000,
            "n": 14
        },
        {
            "v": 11562,
            "vw": 0.1292,
            "o": 0.1275,
            "c": 0.13,
            "h": 0.13,
            "l": 0.1221,
            "t": 1743739200000,
            "n": 46
        },
        {
            "v": 151164,
            "vw": 0.1168,
            "o": 0.13,
            "c": 0.1301,
            "h": 0.139999,
            "l": 0.0902,
            "t": 1743998400000,
            "n": 21
        },
        {
            "v": 428,
            "vw": 0.1363,
            "o": 0.14,
            "c": 0.14,
            "h": 0.14,
            "l": 0.14,
            "t": 1744084800000,
            "n": 11
        },
        {
            "v": 9667,
            "vw": 0.1273,
            "o": 0.1318,
            "c": 0.107,
            "h": 0.135,
            "l": 0.107,
            "t": 1744171200000,
            "n": 33
        },
        {
            "v": 2518,
            "vw": 0.1175,
            "o": 0.124,
            "c": 0.106,
            "h": 0.13,
            "l": 0.106,
            "t": 1744344000000,
            "n": 33
        },
        {
            "v": 151517,
            "vw": 0.1001,
            "o": 0.1001,
            "c": 0.1001,
            "h": 0.1001,
            "l": 0.1001,
            "t": 1744603200000,
            "n": 10
        },
        {
            "v": 437,
            "vw": 0.1263,
            "o": 0.13,
            "c": 0.13,
            "h": 0.13,
            "l": 0.13,
            "t": 1744689600000,
            "n": 8
        },
        {
            "v": 1046,
            "vw": 0.1138,
            "o": 0.10001,
            "c": 0.124,
            "h": 0.13,
            "l": 0.10001,
            "t": 1744776000000,
            "n": 25
        },
        {
            "v": 1545,
            "vw": 0.1289,
            "o": 0.13,
            "c": 0.13,
            "h": 0.13,
            "l": 0.1266,
            "t": 1744862400000,
            "n": 15
        },
        {
            "v": 2239,
            "vw": 0.131,
            "o": 0.13,
            "c": 0.13,
            "h": 0.135,
            "l": 0.13,
            "t": 1745208000000,
            "n": 8
        },
        {
            "v": 241,
            "vw": 0.1276,
            "o": 0.1275,
            "c": 0.1276,
            "h": 0.1276,
            "l": 0.1275,
            "t": 1745294400000,
            "n": 4
        },
        {
            "v": 383,
            "vw": 0.129,
            "o": 0.13,
            "c": 0.1278,
            "h": 0.13,
            "l": 0.1278,
            "t": 1745467200000,
            "n": 4
        },
        {
            "v": 2181,
            "vw": 0.1247,
            "o": 0.124,
            "c": 0.12,
            "h": 0.13,
            "l": 0.12,
            "t": 1745553600000,
            "n": 25
        },
        {
            "v": 483,
            "vw": 0.118,
            "o": 0.12,
            "c": 0.12,
            "h": 0.12,
            "l": 0.12,
            "t": 1745812800000,
            "n": 3
        },
        {
            "v": 514,
            "vw": 0.1191,
            "o": 0.118,
            "c": 0.12,
            "h": 0.12,
            "l": 0.118,
            "t": 1745899200000,
            "n": 7
        },
        {
            "v": 8932,
            "vw": 0.1105,
            "o": 0.13,
            "c": 0.1101,
            "h": 0.13,
            "l": 0.1101,
            "t": 1745985600000,
            "n": 2
        },
        {
            "v": 770,
            "vw": 0.1101,
            "o": 0.11,
            "c": 0.11,
            "h": 0.11,
            "l": 0.11,
            "t": 1746072000000,
            "n": 21
        },
        {
            "v": 130,
            "vw": 0.1102,
            "o": 0.1102,
            "c": 0.1102,
            "h": 0.1102,
            "l": 0.1102,
            "t": 1746158400000,
            "n": 1
        },
        {
            "v": 395,
            "vw": 0.13,
            "o": 0.13,
            "c": 0.13,
            "h": 0.13,
            "l": 0.13,
            "t": 1746417600000,
            "n": 1
        },
        {
            "v": 1439,
            "vw": 0.127,
            "o": 0.13,
            "c": 0.128,
            "h": 0.13,
            "l": 0.128,
            "t": 1746504000000,
            "n": 25
        },
        {
            "v": 395,
            "vw": 0.128,
            "o": 0.13,
            "c": 0.126,
            "h": 0.13,
            "l": 0.126,
            "t": 1746590400000,
            "n": 4
        },
        {
            "v": 8400,
            "vw": 0.13,
            "o": 0.13,
            "c": 0.13,
            "h": 0.13,
            "l": 0.13,
            "t": 1746676800000,
            "n": 10
        },
        {
            "v": 117,
            "vw": 0.14,
            "o": 0.14,
            "c": 0.14,
            "h": 0.14,
            "l": 0.14,
            "t": 1746763200000,
            "n": 2
        },
        {
            "v": 1320,
            "vw": 0.1262,
            "o": 0.13,
            "c": 0.12,
            "h": 0.13,
            "l": 0.12,
            "t": 1747022400000,
            "n": 26
        },
        {
            "v": 4090,
            "vw": 0.1298,
            "o": 0.12,
            "c": 0.13,
            "h": 0.13,
            "l": 0.12,
            "t": 1747108800000,
            "n": 25
        },
        {
            "v": 3095,
            "vw": 0.13,
            "o": 0.13,
            "c": 0.13,
            "h": 0.1303,
            "l": 0.13,
            "t": 1747281600000,
            "n": 22
        },
        {
            "v": 6512,
            "vw": 0.13,
            "o": 0.13,
            "c": 0.13,
            "h": 0.13,
            "l": 0.13,
            "t": 1747368000000,
            "n": 5
        },
        {
            "v": 18208,
            "vw": 0.1493,
            "o": 0.14,
            "c": 0.15,
            "h": 0.15,
            "l": 0.14,
            "t": 1747627200000,
            "n": 34
        },
        {
            "v": 5206,
            "vw": 0.1404,
            "o": 0.15,
            "c": 0.14,
            "h": 0.15,
            "l": 0.14,
            "t": 1747713600000,
            "n": 22
        },
        {
            "v": 400,
            "vw": 0.15,
            "o": 0.15,
            "c": 0.15,
            "h": 0.15,
            "l": 0.15,
            "t": 1747800000000,
            "n": 2
        },
        {
            "v": 610,
            "vw": 0.1497,
            "o": 0.15,
            "c": 0.15,
            "h": 0.15,
            "l": 0.15,
            "t": 1748318400000,
            "n": 3
        },
        {
            "v": 690,
            "vw": 0.1428,
            "o": 0.14,
            "c": 0.15,
            "h": 0.15,
            "l": 0.14,
            "t": 1748404800000,
            "n": 4
        },
        {
            "v": 20950,
            "vw": 0.1402,
            "o": 0.14,
            "c": 0.1475,
            "h": 0.15,
            "l": 0.14,
            "t": 1749009600000,
            "n": 7
        },
        {
            "v": 1481,
            "vw": 0.1404,
            "o": 0.15,
            "c": 0.13,
            "h": 0.15,
            "l": 0.13,
            "t": 1749096000000,
            "n": 8
        },
        {
            "v": 175040,
            "vw": 0.1403,
            "o": 0.14,
            "c": 0.15,
            "h": 0.15,
            "l": 0.13,
            "t": 1749614400000,
            "n": 109
        },
        {
            "v": 263158,
            "vw": 0.1496,
            "o": 0.15,
            "c": 0.133,
            "h": 0.15,
            "l": 0.133,
            "t": 1749787200000,
            "n": 31
        },
        {
            "v": 300,
            "vw": 0.1409,
            "o": 0.1499,
            "c": 0.13,
            "h": 0.1499,
            "l": 0.13,
            "t": 1750392000000,
            "n": 3
        },
        {
            "v": 345,
            "vw": 0.1403,
            "o": 0.15,
            "c": 0.13,
            "h": 0.15,
            "l": 0.13,
            "t": 1750651200000,
            "n": 7
        },
        {
            "v": 3539,
            "vw": 0.1261,
            "o": 0.13,
            "c": 0.1201,
            "h": 0.1302,
            "l": 0.1201,
            "t": 1750910400000,
            "n": 6
        },
        {
            "v": 214,
            "vw": 0.1203,
            "o": 0.1201,
            "c": 0.1202,
            "h": 0.1202,
            "l": 0.1201,
            "t": 1751256000000,
            "n": 6
        },
        {
            "v": 773,
            "vw": 0.1286,
            "o": 0.1286,
            "c": 0.1286,
            "h": 0.1286,
            "l": 0.1286,
            "t": 1751428800000,
            "n": 1
        }
    ],
    "status": "DELAYED",
    "request_id": "532e7632154958ca045dcb05cebdec15",
    "count": 64
}