{
    "ticker": "DYCQR",
    "queryCount": 61,
    "resultsCount": 61,
    "adjusted": true,
    "results": [
        {
            "v": 1206237.0,
            "vw": 0.1807,
            "o": 0.17,
            "c": 0.19,
            "h": 0.23,
            "l": 0.17,
            "t": 1712894400000,
            "n": 129
        },
        {
            "v": 80240,
            "vw": 0.1952,
            "o": 0.2,
            "c": 0.19,
            "h": 0.2,
            "l": 0.19,
            "t": 1713153600000,
            "n": 279
        },
        {
            "v": 396873,
            "vw": 0.1781,
            "o": 0.2,
            "c": 0.18,
            "h": 0.2,
            "l": 0.175,
            "t": 1713240000000,
            "n": 8
        },
        {
            "v": 25640,
            "vw": 0.1799,
            "o": 0.1801,
            "c": 0.1801,
            "h": 0.1801,
            "l": 0.18,
            "t": 1713931200000,
            "n": 34
        },
        {
            "v": 3000,
            "vw": 0.18,
            "o": 0.18,
            "c": 0.18,
            "h": 0.18,
            "l": 0.18,
            "t": 1714363200000,
            "n": 1
        },
        {
            "v": 4000,
            "vw": 0.18,
            "o": 0.18,
            "c": 0.18,
            "h": 0.18,
            "l": 0.18,
            "t": 1714449600000,
            "n": 7
        },
        {
            "v": 3000,
            "vw": 0.18,
            "o": 0.18,
            "c": 0.18,
            "h": 0.18,
            "l": 0.18,
            "t": 1714536000000,
            "n": 12
        },
        {
            "v": 5365,
            "vw": 0.18,
            "o": 0.18,
            "c": 0.18,
            "h": 0.18,
            "l": 0.18,
            "t": 1714622400000,
            "n": 16
        },
        {
            "v": 28673,
            "vw": 0.18,
            "o": 0.18,
            "c": 0.18,
            "h": 0.18,
            "l": 0.18,
            "t": 1714968000000,
            "n": 13
        },
        {
            "v": 44300,
            "vw": 0.18,
            "o": 0.18,
            "c": 0.1801,
            "h": 0.1801,
            "l": 0.18,
            "t": 1715659200000,
            "n": 10
        },
        {
            "v": 700,
            "vw": 0.2057,
            "o": 0.2,
            "c": 0.22,
            "h": 0.22,
            "l": 0.2,
            "t": 1715745600000,
            "n": 2
        },
        {
            "v": 100,
            "vw": 0.2,
            "o": 0.2,
            "c": 0.2,
            "h": 0.2,
            "l": 0.2,
            "t": 1718683200000,
            "n": 1
        },
        {
            "v": 95000,
            "vw": 0.2,
            "o": 0.2,
            "c": 0.2,
            "h": 0.2,
            "l": 0.2,
            "t": 1718856000000,
            "n": 49
        },
        {
            "v": 100,
            "vw": 0.22,
            "o": 0.22,
            "c": 0.22,
            "h": 0.22,
            "l": 0.22,
            "t": 1719201600000,
            "n": 1
        },
        {
            "v": 35010,
            "vw": 0.3032,
            "o": 0.2316,
            "c": 0.29,
            "h": 0.5814,
            "l": 0.216,
            "t": 1719374400000,
            "n": 419
        },
        {
            "v": 14713,
            "vw": 0.2893,
            "o": 0.22,
            "c": 0.29,
            "h": 0.3325,
            "l": 0.22,
            "t": 1719460800000,
            "n": 80
        },
        {
            "v": 18583,
            "vw": 0.29,
            "o": 0.3,
            "c": 0.3136,
            "h": 0.33,
            "l": 0.28,
            "t": 1719547200000,
            "n": 190
        },
        {
            "v": 2809,
            "vw": 0.2944,
            "o": 0.299,
            "c": 0.227,
            "h": 0.3,
            "l": 0.225,
            "t": 1719806400000,
            "n": 12
        },
        {
            "v": 610,
            "vw": 0.2493,
            "o": 0.2365,
            "c": 0.2673,
            "h": 0.2673,
            "l": 0.2354,
            "t": 1719892800000,
            "n": 14
        },
        {
            "v": 468,
            "vw": 0.2284,
            "o": 0.2248,
            "c": 0.2248,
            "h": 0.2248,
            "l": 0.2248,
            "t": 1721188800000,
            "n": 8
        },
        {
            "v": 1500,
            "vw": 0.25,
            "o": 0.25,
            "c": 0.25,
            "h": 0.25,
            "l": 0.25,
            "t": 1726804800000,
            "n": 2
        },
        {
            "v": 6043,
            "vw": 0.2218,
            "o": 0.25,
            "c": 0.2,
            "h": 0.25,
            "l": 0.1802,
            "t": 1729483200000,
            "n": 32
        },
        {
            "v": 1335,
            "vw": 0.1897,
            "o": 0.19,
            "c": 0.194,
            "h": 0.194,
            "l": 0.184,
            "t": 1729569600000,
            "n": 5
        },
        {
            "v": 1000,
            "vw": 0.1802,
            "o": 0.1802,
            "c": 0.1802,
            "h": 0.1802,
            "l": 0.1802,
            "t": 1730433600000,
            "n": 1
        },
        {
            "v": 3938,
            "vw": 0.1808,
            "o": 0.1914,
            "c": 0.1802,
            "h": 0.1914,
            "l": 0.1802,
            "t": 1730869200000,
            "n": 3
        },
        {
            "v": 5013,
            "vw": 0.1688,
            "o": 0.1839,
            "c": 0.13,
            "h": 0.184,
            "l": 0.13,
            "t": 1731906000000,
            "n": 23
        },
        {
            "v": 2871,
            "vw": 0.1435,
            "o": 0.1479,
            "c": 0.1392,
            "h": 0.16055,
            "l": 0.1391,
            "t": 1731992400000,
            "n": 18
        },
        {
            "v": 383,
            "vw": 0.1145,
            "o": 0.13,
            "c": 0.1,
            "h": 0.13,
            "l": 0.1,
            "t": 1732683600000,
            "n": 5
        },
        {
            "v": 29237,
            "vw": 0.1074,
            "o": 0.1,
            "c": 0.1,
            "h": 0.181,
            "l": 0.05,
            "t": 1732856400000,
            "n": 161
        },
        {
            "v": 501,
            "vw": 0.1453,
            "o": 0.15,
            "c": 0.1311,
            "h": 0.15,
            "l": 0.1311,
            "t": 1733202000000,
            "n": 4
        },
        {
            "v": 600,
            "vw": 0.1484,
            "o": 0.1479,
            "c": 0.1495,
            "h": 0.1495,
            "l": 0.1476,
            "t": 1734325200000,
            "n": 6
        },
        {
            "v": 2700,
            "vw": 0.15,
            "o": 0.15,
            "c": 0.15,
            "h": 0.15,
            "l": 0.15,
            "t": 1735189200000,
            "n": 2
        },
        {
            "v": 3602,
            "vw": 0.1981,
            "o": 0.16,
            "c": 0.2,
            "h": 0.21,
            "l": 0.16,
            "t": 1736312400000,
            "n": 21
        },
        {
            "v": 1200,
            "vw": 0.2208,
            "o": 0.22,
            "c": 0.2225,
            "h": 0.2225,
            "l": 0.22,
            "t": 1737954000000,
            "n": 6
        },
        {
            "v": 1162,
            "vw": 0.24,
            "o": 0.23,
            "c": 0.25,
            "h": 0.25,
            "l": 0.23,
            "t": 1740114000000,
            "n": 10
        },
        {
            "v": 357,
            "vw": 0.2362,
            "o": 0.23,
            "c": 0.23,
            "h": 0.23,
            "l": 0.23,
            "t": 1740546000000,
            "n": 7
        },
        {
            "v": 9841,
            "vw": 0.262,
            "o": 0.24,
            "c": 0.23,
            "h": 0.2949,
            "l": 0.2199,
            "t": 1740632400000,
            "n": 73
        },
        {
            "v": 58221,
            "vw": 0.2536,
            "o": 0.2396,
            "c": 0.19,
            "h": 0.2999,
            "l": 0.19,
            "t": 1740718800000,
            "n": 392
        },
        {
            "v": 3900,
            "vw": 0.1928,
            "o": 0.19,
            "c": 0.19,
            "h": 0.19,
            "l": 0.19,
            "t": 1740978000000,
            "n": 3
        },
        {
            "v": 200,
            "vw": 0.1959,
            "o": 0.196,
            "c": 0.1959,
            "h": 0.196,
            "l": 0.1959,
            "t": 1741237200000,
            "n": 2
        },
        {
            "v": 1162,
            "vw": 0.1911,
            "o": 0.196,
            "c": 0.1901,
            "h": 0.196,
            "l": 0.1901,
            "t": 1741323600000,
            "n": 3
        },
        {
            "v": 7510,
            "vw": 0.2197,
            "o": 0.2145,
            "c": 0.22,
            "h": 0.22,
            "l": 0.214,
            "t": 1742184000000,
            "n": 12
        },
        {
            "v": 1099,
            "vw": 0.22,
            "o": 0.22,
            "c": 0.22,
            "h": 0.22,
            "l": 0.2199,
            "t": 1742270400000,
            "n": 11
        },
        {
            "v": 14247,
            "vw": 0.2204,
            "o": 0.22,
            "c": 0.22,
            "h": 0.224,
            "l": 0.22,
            "t": 1742356800000,
            "n": 29
        },
        {
            "v": 623,
            "vw": 0.2204,
            "o": 0.22,
            "c": 0.22,
            "h": 0.22,
            "l": 0.22,
            "t": 1742443200000,
            "n": 5
        },
        {
            "v": 524,
            "vw": 0.2222,
            "o": 0.22,
            "c": 0.22,
            "h": 0.22,
            "l": 0.22,
            "t": 1742529600000,
            "n": 8
        },
        {
            "v": 783,
            "vw": 0.2246,
            "o": 0.22,
            "c": 0.23,
            "h": 0.23,
            "l": 0.22,
            "t": 1742788800000,
            "n": 7
        },
        {
            "v": 625,
            "vw": 0.225,
            "o": 0.22,
            "c": 0.232,
            "h": 0.232,
            "l": 0.22,
            "t": 1742875200000,
            "n": 6
        },
        {
            "v": 644,
            "vw": 0.24,
            "o": 0.24,
            "c": 0.24,
            "h": 0.24,
            "l": 0.24,
            "t": 1742961600000,
            "n": 8
        },
        {
            "v": 100,
            "vw": 0.23,
            "o": 0.23,
            "c": 0.23,
            "h": 0.23,
            "l": 0.23,
            "t": 1744084800000,
            "n": 1
        },
        {
            "v": 100000,
            "vw": 0.22,
            "o": 0.22,
            "c": 0.22,
            "h": 0.22,
            "l": 0.22,
            "t": 1744257600000,
            "n": 2
        },
        {
            "v": 500,
            "vw": 0.1964,
            "o": 0.2,
            "c": 0.182,
            "h": 0.2,
            "l": 0.182,
            "t": 1745208000000,
            "n": 5
        },
        {
            "v": 493,
            "vw": 0.2156,
            "o": 0.2085,
            "c": 0.2085,
            "h": 0.2085,
            "l": 0.2085,
            "t": 1745380800000,
            "n": 9
        },
        {
            "v": 250000,
            "vw": 0.16,
            "o": 0.16,
            "c": 0.16,
            "h": 0.16,
            "l": 0.16,
            "t": 1748923200000,
            "n": 1
        },
        {
            "v": 30040,
            "vw": 0.1604,
            "o": 0.18,
            "c": 0.16,
            "h": 0.18,
            "l": 0.16,
            "t": 1749528000000,
            "n": 7
        },
        {
            "v": 1000,
            "vw": 0.1606,
            "o": 0.1611,
            "c": 0.16,
            "h": 0.1611,
            "l": 0.16,
            "t": 1750219200000,
            "n": 2
        },
        {
            "v": 600,
            "vw": 0.1622,
            "o": 0.1667,
            "c": 0.16,
            "h": 0.1667,
            "l": 0.16,
            "t": 1750392000000,
            "n": 4
        },
        {
            "v": 45462,
            "vw": 0.1594,
            "o": 0.1611,
            "c": 0.1551,
            "h": 0.1634,
            "l": 0.155,
            "t": 1750737600000,
            "n": 16
        },
        {
            "v": 60320,
            "vw": 0.155,
            "o": 0.155,
            "c": 0.155,
            "h": 0.16,
            "l": 0.1503,
            "t": 1750824000000,
            "n": 40
        },
        {
            "v": 2341,
            "vw": 0.2065,
            "o": 0.2061,
            "c": 0.17,
            "h": 0.22,
            "l": 0.17,
            "t": 1751256000000,
            "n": 22
        },
        {
            "v": 101185,
            "vw": 0.1595,
            "o": 0.17,
            "c": 0.16,
            "h": 0.17,
            "l": 0.1367,
            "t": 1751342400000,
            "n": 26
        }
    ],
    "status": "DELAYED",
    "request_id": "6c7fdd831b9020e7662b62639603abfa",
    "count": 61
}